[
   {
      "RouteName" : "58",
      "GoBack" : "1",
      "PT" : [
         {
            "OrderNo" : "1",
            "Lat" : "24.119182",
            "Lon" : "120.654237"
         },
         {
            "OrderNo" : "2",
            "Lat" : "24.119632",
            "Lon" : "120.654731"
         },
         {
            "OrderNo" : "3",
            "Lat" : "24.120749",
            "Lon" : "120.653679"
         },
         {
            "OrderNo" : "4",
            "Lat" : "24.121454",
            "Lon" : "120.654838"
         },
         {
            "OrderNo" : "5",
            "Lat" : "24.117537",
            "Lon" : "120.658357"
         },
         {
            "OrderNo" : "6",
            "Lat" : "24.117027",
            "Lon" : "120.659301"
         },
         {
            "OrderNo" : "7",
            "Lat" : "24.11691",
            "Lon" : "120.660481"
         },
         {
            "OrderNo" : "8",
            "Lat" : "24.113306",
            "Lon" : "120.660481"
         },
         {
            "OrderNo" : "9",
            "Lat" : "24.113189",
            "Lon" : "120.661855"
         },
         {
            "OrderNo" : "10",
            "Lat" : "24.114893",
            "Lon" : "120.67003"
         },
         {
            "OrderNo" : "11",
            "Lat" : "24.115069",
            "Lon" : "120.679343"
         },
         {
            "OrderNo" : "12",
            "Lat" : "24.119182",
            "Lon" : "120.679364"
         },
         {
            "OrderNo" : "13",
            "Lat" : "24.119143",
            "Lon" : "120.684128"
         },
         {
            "OrderNo" : "14",
            "Lat" : "24.123187",
            "Lon" : "120.684106"
         },
         {
            "OrderNo" : "15",
            "Lat" : "24.124567",
            "Lon" : "120.684149"
         },
         {
            "OrderNo" : "16",
            "Lat" : "24.12621",
            "Lon" : "120.68424"
         },
         {
            "OrderNo" : "17",
            "Lat" : "24.12638",
            "Lon" : "120.6842"
         },
         {
            "OrderNo" : "18",
            "Lat" : "24.12638",
            "Lon" : "120.6842"
         },
         {
            "OrderNo" : "19",
            "Lat" : "24.12984",
            "Lon" : "120.68514"
         },
         {
            "OrderNo" : "20",
            "Lat" : "24.13001",
            "Lon" : "120.68514"
         },
         {
            "OrderNo" : "21",
            "Lat" : "24.13139",
            "Lon" : "120.68449"
         },
         {
            "OrderNo" : "22",
            "Lat" : "24.13197",
            "Lon" : "120.68413"
         },
         {
            "OrderNo" : "23",
            "Lat" : "24.13318",
            "Lon" : "120.68355"
         },
         {
            "OrderNo" : "24",
            "Lat" : "24.13318",
            "Lon" : "120.68355"
         },
         {
            "OrderNo" : "25",
            "Lat" : "24.135906",
            "Lon" : "120.68224"
         },
         {
            "OrderNo" : "26",
            "Lat" : "24.136806",
            "Lon" : "120.684128"
         },
         {
            "OrderNo" : "27",
            "Lat" : "24.137511",
            "Lon" : "120.684578"
         },
         {
            "OrderNo" : "28",
            "Lat" : "24.138686",
            "Lon" : "120.685844"
         },
         {
            "OrderNo" : "29",
            "Lat" : "24.139391",
            "Lon" : "120.685973"
         },
         {
            "OrderNo" : "30",
            "Lat" : "24.14011",
            "Lon" : "120.68589"
         },
         {
            "OrderNo" : "31",
            "Lat" : "24.14011",
            "Lon" : "120.68589"
         },
         {
            "OrderNo" : "32",
            "Lat" : "24.14028",
            "Lon" : "120.686"
         },
         {
            "OrderNo" : "33",
            "Lat" : "24.14345",
            "Lon" : "120.68593"
         },
         {
            "OrderNo" : "34",
            "Lat" : "24.14409",
            "Lon" : "120.68615"
         },
         {
            "OrderNo" : "35",
            "Lat" : "24.14409",
            "Lon" : "120.68615"
         },
         {
            "OrderNo" : "36",
            "Lat" : "24.14517",
            "Lon" : "120.6865"
         },
         {
            "OrderNo" : "37",
            "Lat" : "24.14558",
            "Lon" : "120.6865"
         },
         {
            "OrderNo" : "38",
            "Lat" : "24.14608",
            "Lon" : "120.68625"
         },
         {
            "OrderNo" : "39",
            "Lat" : "24.14618",
            "Lon" : "120.68601"
         },
         {
            "OrderNo" : "40",
            "Lat" : "24.14618",
            "Lon" : "120.68601"
         },
         {
            "OrderNo" : "41",
            "Lat" : "24.146264",
            "Lon" : "120.684128"
         },
         {
            "OrderNo" : "42",
            "Lat" : "24.145931",
            "Lon" : "120.683162"
         },
         {
            "OrderNo" : "43",
            "Lat" : "24.146029",
            "Lon" : "120.682518"
         },
         {
            "OrderNo" : "44",
            "Lat" : "24.14907",
            "Lon" : "120.68375"
         },
         {
            "OrderNo" : "45",
            "Lat" : "24.14907",
            "Lon" : "120.68375"
         },
         {
            "OrderNo" : "46",
            "Lat" : "24.15469",
            "Lon" : "120.68617"
         },
         {
            "OrderNo" : "47",
            "Lat" : "24.15469",
            "Lon" : "120.68617"
         },
         {
            "OrderNo" : "48",
            "Lat" : "24.15493",
            "Lon" : "120.68617"
         },
         {
            "OrderNo" : "49",
            "Lat" : "24.15728",
            "Lon" : "120.6851"
         },
         {
            "OrderNo" : "50",
            "Lat" : "24.15785",
            "Lon" : "120.68508"
         },
         {
            "OrderNo" : "51",
            "Lat" : "24.15785",
            "Lon" : "120.68508"
         },
         {
            "OrderNo" : "52",
            "Lat" : "24.16691",
            "Lon" : "120.6851"
         },
         {
            "OrderNo" : "53",
            "Lat" : "24.16702",
            "Lon" : "120.68504"
         },
         {
            "OrderNo" : "54",
            "Lat" : "24.16702",
            "Lon" : "120.68504"
         },
         {
            "OrderNo" : "55",
            "Lat" : "24.16707",
            "Lon" : "120.6851"
         },
         {
            "OrderNo" : "56",
            "Lat" : "24.16818",
            "Lon" : "120.6852"
         },
         {
            "OrderNo" : "57",
            "Lat" : "24.16818",
            "Lon" : "120.6852"
         },
         {
            "OrderNo" : "58",
            "Lat" : "24.16832",
            "Lon" : "120.68521"
         },
         {
            "OrderNo" : "59",
            "Lat" : "24.16844",
            "Lon" : "120.68515"
         },
         {
            "OrderNo" : "60",
            "Lat" : "24.16844",
            "Lon" : "120.68515"
         },
         {
            "OrderNo" : "61",
            "Lat" : "24.1752",
            "Lon" : "120.68568"
         },
         {
            "OrderNo" : "62",
            "Lat" : "24.1752",
            "Lon" : "120.68568"
         },
         {
            "OrderNo" : "63",
            "Lat" : "24.18153",
            "Lon" : "120.68613"
         },
         {
            "OrderNo" : "64",
            "Lat" : "24.18153",
            "Lon" : "120.68613"
         },
         {
            "OrderNo" : "65",
            "Lat" : "24.18268",
            "Lon" : "120.68616"
         },
         {
            "OrderNo" : "66",
            "Lat" : "24.18268",
            "Lon" : "120.68616"
         },
         {
            "OrderNo" : "67",
            "Lat" : "24.193038",
            "Lon" : "120.686414"
         },
         {
            "OrderNo" : "68",
            "Lat" : "24.19352",
            "Lon" : "120.68644"
         },
         {
            "OrderNo" : "69",
            "Lat" : "24.19352",
            "Lon" : "120.68644"
         },
         {
            "OrderNo" : "70",
            "Lat" : "24.19836",
            "Lon" : "120.68654"
         },
         {
            "OrderNo" : "71",
            "Lat" : "24.19836",
            "Lon" : "120.68654"
         },
         {
            "OrderNo" : "72",
            "Lat" : "24.20082",
            "Lon" : "120.68664"
         },
         {
            "OrderNo" : "73",
            "Lat" : "24.20524",
            "Lon" : "120.68661"
         },
         {
            "OrderNo" : "74",
            "Lat" : "24.20524",
            "Lon" : "120.68661"
         },
         {
            "OrderNo" : "75",
            "Lat" : "24.2103",
            "Lon" : "120.68673"
         },
         {
            "OrderNo" : "76",
            "Lat" : "24.21137",
            "Lon" : "120.68688"
         },
         {
            "OrderNo" : "77",
            "Lat" : "24.21602",
            "Lon" : "120.68822"
         },
         {
            "OrderNo" : "78",
            "Lat" : "24.21602",
            "Lon" : "120.68822"
         },
         {
            "OrderNo" : "79",
            "Lat" : "24.216",
            "Lon" : "120.68856"
         },
         {
            "OrderNo" : "80",
            "Lat" : "24.216",
            "Lon" : "120.68856"
         },
         {
            "OrderNo" : "81",
            "Lat" : "24.21592",
            "Lon" : "120.69027"
         },
         {
            "OrderNo" : "82",
            "Lat" : "24.21601",
            "Lon" : "120.69533"
         },
         {
            "OrderNo" : "83",
            "Lat" : "24.21604",
            "Lon" : "120.69563"
         },
         {
            "OrderNo" : "84",
            "Lat" : "24.21662",
            "Lon" : "120.69737"
         },
         {
            "OrderNo" : "85",
            "Lat" : "24.21665",
            "Lon" : "120.69759"
         },
         {
            "OrderNo" : "86",
            "Lat" : "24.21642",
            "Lon" : "120.69928"
         },
         {
            "OrderNo" : "87",
            "Lat" : "24.21642",
            "Lon" : "120.69928"
         },
         {
            "OrderNo" : "88",
            "Lat" : "24.215814",
            "Lon" : "120.704121"
         },
         {
            "OrderNo" : "89",
            "Lat" : "24.215677",
            "Lon" : "120.70521"
         },
         {
            "OrderNo" : "90",
            "Lat" : "24.215227",
            "Lon" : "120.705113"
         },
         {
            "OrderNo" : "91",
            "Lat" : "24.2132",
            "Lon" : "120.70534"
         },
         {
            "OrderNo" : "92",
            "Lat" : "24.2132",
            "Lon" : "120.70534"
         },
         {
            "OrderNo" : "93",
            "Lat" : "24.21158",
            "Lon" : "120.70546"
         },
         {
            "OrderNo" : "94",
            "Lat" : "24.21158",
            "Lon" : "120.70546"
         },
         {
            "OrderNo" : "95",
            "Lat" : "24.207124",
            "Lon" : "120.705156"
         },
         {
            "OrderNo" : "96",
            "Lat" : "24.207242",
            "Lon" : "120.70271"
         },
         {
            "OrderNo" : "97",
            "Lat" : "24.207242",
            "Lon" : "120.701637"
         },
         {
            "OrderNo" : "98",
            "Lat" : "24.208768",
            "Lon" : "120.701208"
         },
         {
            "OrderNo" : "99",
            "Lat" : "24.21165",
            "Lon" : "120.70058"
         },
         {
            "OrderNo" : "100",
            "Lat" : "24.21165",
            "Lon" : "120.70058"
         },
         {
            "OrderNo" : "101",
            "Lat" : "24.21336",
            "Lon" : "120.70059"
         }
      ]
   },
   {
      "RouteName" : "58",
      "GoBack" : "2",
      "PT" : [
         {
            "OrderNo" : "1",
            "Lat" : "24.213436",
            "Lon" : "120.700597"
         },
         {
            "OrderNo" : "2",
            "Lat" : "24.211645",
            "Lon" : "120.700554"
         },
         {
            "OrderNo" : "3",
            "Lat" : "24.207203",
            "Lon" : "120.701637"
         },
         {
            "OrderNo" : "4",
            "Lat" : "24.207203",
            "Lon" : "120.702882"
         },
         {
            "OrderNo" : "5",
            "Lat" : "24.207007",
            "Lon" : "120.705242"
         },
         {
            "OrderNo" : "6",
            "Lat" : "24.211459",
            "Lon" : "120.705446"
         },
         {
            "OrderNo" : "7",
            "Lat" : "24.215246",
            "Lon" : "120.705119"
         },
         {
            "OrderNo" : "8",
            "Lat" : "24.215652",
            "Lon" : "120.705221"
         },
         {
            "OrderNo" : "9",
            "Lat" : "24.216226",
            "Lon" : "120.700297"
         },
         {
            "OrderNo" : "10",
            "Lat" : "24.216613",
            "Lon" : "120.697536"
         },
         {
            "OrderNo" : "11",
            "Lat" : "24.215967",
            "Lon" : "120.695504"
         },
         {
            "OrderNo" : "12",
            "Lat" : "24.215902",
            "Lon" : "120.690723"
         },
         {
            "OrderNo" : "13",
            "Lat" : "24.215965",
            "Lon" : "120.68807"
         },
         {
            "OrderNo" : "14",
            "Lat" : "24.210723",
            "Lon" : "120.686698"
         },
         {
            "OrderNo" : "15",
            "Lat" : "24.200901",
            "Lon" : "120.686617"
         },
         {
            "OrderNo" : "16",
            "Lat" : "24.181699",
            "Lon" : "120.686145"
         },
         {
            "OrderNo" : "17",
            "Lat" : "24.172034",
            "Lon" : "120.685421"
         },
         {
            "OrderNo" : "18",
            "Lat" : "24.167076",
            "Lon" : "120.685093"
         },
         {
            "OrderNo" : "19",
            "Lat" : "24.157317",
            "Lon" : "120.685077"
         },
         {
            "OrderNo" : "20",
            "Lat" : "24.15485",
            "Lon" : "120.686204"
         },
         {
            "OrderNo" : "21",
            "Lat" : "24.149097",
            "Lon" : "120.683803"
         },
         {
            "OrderNo" : "22",
            "Lat" : "24.145887",
            "Lon" : "120.682454"
         },
         {
            "OrderNo" : "23",
            "Lat" : "24.145863",
            "Lon" : "120.683044"
         },
         {
            "OrderNo" : "24",
            "Lat" : "24.146269",
            "Lon" : "120.683972"
         },
         {
            "OrderNo" : "25",
            "Lat" : "24.146186",
            "Lon" : "120.686263"
         },
         {
            "OrderNo" : "26",
            "Lat" : "24.145388",
            "Lon" : "120.686563"
         },
         {
            "OrderNo" : "27",
            "Lat" : "24.143454",
            "Lon" : "120.68592"
         },
         {
            "OrderNo" : "28",
            "Lat" : "24.138887",
            "Lon" : "120.686059"
         },
         {
            "OrderNo" : "29",
            "Lat" : "24.137835",
            "Lon" : "120.685152"
         },
         {
            "OrderNo" : "30",
            "Lat" : "24.137443",
            "Lon" : "120.684648"
         },
         {
            "OrderNo" : "31",
            "Lat" : "24.136704",
            "Lon" : "120.684203"
         },
         {
            "OrderNo" : "32",
            "Lat" : "24.135818",
            "Lon" : "120.682266"
         },
         {
            "OrderNo" : "33",
            "Lat" : "24.129958",
            "Lon" : "120.685169"
         },
         {
            "OrderNo" : "34",
            "Lat" : "24.126575",
            "Lon" : "120.684246"
         },
         {
            "OrderNo" : "35",
            "Lat" : "24.12443",
            "Lon" : "120.683506"
         },
         {
            "OrderNo" : "36",
            "Lat" : "24.123275",
            "Lon" : "120.684106"
         },
         {
            "OrderNo" : "37",
            "Lat" : "24.119828",
            "Lon" : "120.684085"
         },
         {
            "OrderNo" : "38",
            "Lat" : "24.119182",
            "Lon" : "120.68372"
         },
         {
            "OrderNo" : "39",
            "Lat" : "24.119084",
            "Lon" : "120.679386"
         },
         {
            "OrderNo" : "40",
            "Lat" : "24.115089",
            "Lon" : "120.679321"
         },
         {
            "OrderNo" : "41",
            "Lat" : "24.114912",
            "Lon" : "120.670159"
         },
         {
            "OrderNo" : "42",
            "Lat" : "24.113267",
            "Lon" : "120.662284"
         },
         {
            "OrderNo" : "43",
            "Lat" : "24.113267",
            "Lon" : "120.660417"
         },
         {
            "OrderNo" : "44",
            "Lat" : "24.116969",
            "Lon" : "120.660481"
         },
         {
            "OrderNo" : "45",
            "Lat" : "24.1169",
            "Lon" : "120.659376"
         },
         {
            "OrderNo" : "46",
            "Lat" : "24.117595",
            "Lon" : "120.658218"
         },
         {
            "OrderNo" : "47",
            "Lat" : "24.120455",
            "Lon" : "120.655696"
         },
         {
            "OrderNo" : "48",
            "Lat" : "24.119583",
            "Lon" : "120.654688"
         },
         {
            "OrderNo" : "49",
            "Lat" : "24.11879",
            "Lon" : "120.653915"
         }
      ]
   }
]
