<?xml version="1.0" encoding="UTF-8" standalone="yes"?>
<BusDynInfo><EssentialInfo><Location><name>TCBUS</name><CenterName>Maxwin</CenterName></Location><UpdateTime>2014-12-20 07:52:57</UpdateTime><CoordinateSystem/></EssentialInfo>
<Routes><Route RouteName="102" GoBack="1"><PT OrderNo="1" Lat="24.138356" Lon="120.68563"/><PT OrderNo="2" Lat="24.137322" Lon="120.684556"/><PT OrderNo="3" Lat="24.136732" Lon="120.684159"/><PT OrderNo="4" Lat="24.135842" Lon="120.68225"/><PT OrderNo="5" Lat="24.134401" Lon="120.682951"/><PT OrderNo="6" Lat="24.131837" Lon="120.676596"/><PT OrderNo="7" Lat="24.130141" Lon="120.672585"/><PT OrderNo="8" Lat="24.127838" Lon="120.667115"/><PT OrderNo="9" Lat="24.127354" Lon="120.666157"/><PT OrderNo="10" Lat="24.126323" Lon="120.664999"/><PT OrderNo="11" Lat="24.122221" Lon="120.661884"/><PT OrderNo="12" Lat="24.11895" Lon="120.659399"/><PT OrderNo="13" Lat="24.11846" Lon="120.659047"/><PT OrderNo="14" Lat="24.117652" Lon="120.658378"/><PT OrderNo="15" Lat="24.114547" Lon="120.654528"/><PT OrderNo="16" Lat="24.113093" Lon="120.652583"/><PT OrderNo="17" Lat="24.11216" Lon="120.65089"/><PT OrderNo="18" Lat="24.11168" Lon="120.650167"/><PT OrderNo="19" Lat="24.111146" Lon="120.648505"/><PT OrderNo="20" Lat="24.109697" Lon="120.644127"/><PT OrderNo="21" Lat="24.108801" Lon="120.641279"/><PT OrderNo="22" Lat="24.107383" Lon="120.63674"/><PT OrderNo="23" Lat="24.106765" Lon="120.634923"/><PT OrderNo="24" Lat="24.105184" Lon="120.63166"/><PT OrderNo="25" Lat="24.106067" Lon="120.626343"/><PT OrderNo="26" Lat="24.106272" Lon="120.625"/><PT OrderNo="27" Lat="24.106498" Lon="120.621174"/><PT OrderNo="28" Lat="24.10658" Lon="120.619228"/><PT OrderNo="29" Lat="24.106457" Lon="120.618534"/><PT OrderNo="30" Lat="24.105883" Lon="120.615957"/><PT OrderNo="31" Lat="24.106706" Lon="120.614026"/><PT OrderNo="32" Lat="24.111563" Lon="120.618339"/><PT OrderNo="33" Lat="24.11174" Lon="120.616322"/><PT OrderNo="34" Lat="24.110133" Lon="120.616128"/><PT OrderNo="35" Lat="24.110153" Lon="120.615635"/><PT OrderNo="36" Lat="24.110427" Lon="120.615356"/><PT OrderNo="37" Lat="24.11409" Lon="120.615635"/><PT OrderNo="38" Lat="24.114129" Lon="120.614305"/><PT OrderNo="39" Lat="24.115539" Lon="120.612931"/><PT OrderNo="40" Lat="24.113659" Lon="120.610657"/><PT OrderNo="41" Lat="24.112249" Lon="120.61173"/><PT OrderNo="42" Lat="24.110564" Lon="120.611472"/><PT OrderNo="43" Lat="24.107587" Lon="120.611129"/><PT OrderNo="44" Lat="24.108076" Lon="120.608952"/><PT OrderNo="45" Lat="24.109258" Lon="120.605415"/><PT OrderNo="46" Lat="24.111114" Lon="120.599643"/><PT OrderNo="47" Lat="24.113319" Lon="120.592922"/><PT OrderNo="48" Lat="24.113683" Lon="120.591385"/><PT OrderNo="49" Lat="24.113431" Lon="120.588562"/><PT OrderNo="50" Lat="24.113181" Lon="120.587391"/><PT OrderNo="51" Lat="24.113305" Lon="120.586681"/><PT OrderNo="52" Lat="24.113726" Lon="120.585689"/><PT OrderNo="53" Lat="24.114149" Lon="120.5852"/><PT OrderNo="54" Lat="24.115777" Lon="120.584093"/><PT OrderNo="55" Lat="24.116285" Lon="120.583318"/><PT OrderNo="56" Lat="24.117521" Lon="120.580063"/><PT OrderNo="57" Lat="24.118976" Lon="120.576284"/><PT OrderNo="58" Lat="24.12012" Lon="120.573187"/><PT OrderNo="59" Lat="24.121311" Lon="120.570146"/><PT OrderNo="60" Lat="24.122786" Lon="120.566217"/><PT OrderNo="61" Lat="24.123363" Lon="120.564686"/><PT OrderNo="62" Lat="24.125071" Lon="120.561854"/><PT OrderNo="63" Lat="24.127114" Lon="120.558479"/><PT OrderNo="64" Lat="24.128326" Lon="120.556473"/><PT OrderNo="65" Lat="24.128888" Lon="120.555804"/><PT OrderNo="66" Lat="24.129644" Lon="120.555246"/><PT OrderNo="67" Lat="24.131293" Lon="120.554521"/><PT OrderNo="68" Lat="24.133405" Lon="120.554108"/><PT OrderNo="69" Lat="24.134686" Lon="120.553801"/><PT OrderNo="70" Lat="24.136216" Lon="120.552666"/><PT OrderNo="71" Lat="24.138387" Lon="120.550988"/><PT OrderNo="72" Lat="24.138815" Lon="120.550652"/><PT OrderNo="73" Lat="24.141562" Lon="120.549047"/><PT OrderNo="74" Lat="24.143681" Lon="120.54802"/><PT OrderNo="75" Lat="24.14616" Lon="120.546913"/><PT OrderNo="76" Lat="24.148161" Lon="120.546349"/><PT OrderNo="77" Lat="24.150887" Lon="120.54566"/><PT OrderNo="78" Lat="24.151946" Lon="120.545368"/><PT OrderNo="79" Lat="24.152262" Lon="120.545247"/><PT OrderNo="80" Lat="24.153392" Lon="120.544893"/><PT OrderNo="81" Lat="24.155092" Lon="120.544375"/><PT OrderNo="82" Lat="24.156489" Lon="120.544271"/><PT OrderNo="83" Lat="24.158308" Lon="120.544167"/><PT OrderNo="84" Lat="24.159885" Lon="120.543837"/><PT OrderNo="85" Lat="24.161478" Lon="120.543527"/><PT OrderNo="86" Lat="24.162632" Lon="120.54334"/><PT OrderNo="87" Lat="24.163353" Lon="120.543203"/><PT OrderNo="88" Lat="24.164481" Lon="120.542965"/><PT OrderNo="89" Lat="24.166155" Lon="120.542612"/><PT OrderNo="90" Lat="24.168173" Lon="120.542591"/><PT OrderNo="91" Lat="24.169018" Lon="120.542601"/><PT OrderNo="92" Lat="24.170774" Lon="120.542824"/><PT OrderNo="93" Lat="24.174048" Lon="120.543703"/><PT OrderNo="94" Lat="24.17544" Lon="120.544057"/><PT OrderNo="95" Lat="24.177444" Lon="120.544567"/><PT OrderNo="96" Lat="24.179243" Lon="120.54503"/><PT OrderNo="97" Lat="24.18127" Lon="120.545553"/><PT OrderNo="98" Lat="24.18175" Lon="120.545667"/><PT OrderNo="99" Lat="24.181878" Lon="120.545063"/><PT OrderNo="100" Lat="24.182441" Lon="120.545106"/><PT OrderNo="101" Lat="24.183653" Lon="120.545096"/><PT OrderNo="102" Lat="24.185965" Lon="120.545079"/><PT OrderNo="103" Lat="24.187544" Lon="120.545272"/><PT OrderNo="104" Lat="24.189537" Lon="120.545463"/><PT OrderNo="105" Lat="24.192159" Lon="120.545715"/><PT OrderNo="106" Lat="24.194016" Lon="120.545903"/><PT OrderNo="107" Lat="24.196847" Lon="120.546213"/><PT OrderNo="108" Lat="24.198389" Lon="120.546412"/><PT OrderNo="109" Lat="24.199885" Lon="120.546872"/><PT OrderNo="110" Lat="24.201368" Lon="120.54729"/><PT OrderNo="111" Lat="24.202779" Lon="120.547738"/><PT OrderNo="112" Lat="24.20408" Lon="120.548174"/><PT OrderNo="113" Lat="24.206104" Lon="120.548452"/><PT OrderNo="114" Lat="24.207497" Lon="120.549057"/><PT OrderNo="115" Lat="24.209823" Lon="120.55007"/><PT OrderNo="116" Lat="24.211199" Lon="120.550697"/><PT OrderNo="117" Lat="24.212678" Lon="120.551227"/><PT OrderNo="118" Lat="24.214616" Lon="120.551728"/><PT OrderNo="119" Lat="24.216338" Lon="120.552433"/><PT OrderNo="120" Lat="24.217027" Lon="120.552774"/><PT OrderNo="121" Lat="24.218565" Lon="120.55391"/><PT OrderNo="122" Lat="24.220035" Lon="120.555112"/><PT OrderNo="123" Lat="24.221133" Lon="120.555951"/><PT OrderNo="124" Lat="24.22173" Lon="120.556224"/><PT OrderNo="125" Lat="24.224549" Lon="120.557289"/><PT OrderNo="126" Lat="24.226341" Lon="120.557877"/><PT OrderNo="127" Lat="24.227784" Lon="120.55837"/><PT OrderNo="128" Lat="24.229333" Lon="120.558327"/><PT OrderNo="129" Lat="24.231311" Lon="120.558576"/><PT OrderNo="130" Lat="24.233567" Lon="120.558412"/><PT OrderNo="131" Lat="24.234045" Lon="120.558409"/><PT OrderNo="132" Lat="24.236044" Lon="120.559064"/><PT OrderNo="133" Lat="24.237173" Lon="120.55942"/><PT OrderNo="134" Lat="24.239059" Lon="120.559841"/><PT OrderNo="135" Lat="24.239394" Lon="120.559945"/></Route>

<Route RouteName="102" GoBack="2"><PT OrderNo="1" Lat="24.239394" Lon="120.559912"/><PT OrderNo="2" Lat="24.238705" Lon="120.559738"/><PT OrderNo="3" Lat="24.23716" Lon="120.559376"/><PT OrderNo="4" Lat="24.234663" Lon="120.55858"/><PT OrderNo="5" Lat="24.233963" Lon="120.558387"/><PT OrderNo="6" Lat="24.233453" Lon="120.558376"/><PT OrderNo="7" Lat="24.231385" Lon="120.558501"/><PT OrderNo="8" Lat="24.229554" Lon="120.558373"/><PT OrderNo="9" Lat="24.227792" Lon="120.558297"/><PT OrderNo="10" Lat="24.224254" Lon="120.557129"/><PT OrderNo="11" Lat="24.221414" Lon="120.556041"/><PT OrderNo="12" Lat="24.216902" Lon="120.552709"/><PT OrderNo="13" Lat="24.21466" Lon="120.551798"/><PT OrderNo="14" Lat="24.212601" Lon="120.551272"/><PT OrderNo="15" Lat="24.209353" Lon="120.549803"/><PT OrderNo="16" Lat="24.207361" Lon="120.548949"/><PT OrderNo="17" Lat="24.206082" Lon="120.548394"/><PT OrderNo="18" Lat="24.204391" Lon="120.548148"/><PT OrderNo="19" Lat="24.203903" Lon="120.548055"/><PT OrderNo="20" Lat="24.201026" Lon="120.547152"/><PT OrderNo="21" Lat="24.198382" Lon="120.546388"/><PT OrderNo="22" Lat="24.196223" Lon="120.546182"/><PT OrderNo="23" Lat="24.193759" Lon="120.545838"/><PT OrderNo="24" Lat="24.191343" Lon="120.545585"/><PT OrderNo="25" Lat="24.187413" Lon="120.545217"/><PT OrderNo="26" Lat="24.185963" Lon="120.545059"/><PT OrderNo="27" Lat="24.182548" Lon="120.545084"/><PT OrderNo="28" Lat="24.181864" Lon="120.545011"/><PT OrderNo="29" Lat="24.181756" Lon="120.545634"/><PT OrderNo="30" Lat="24.175256" Lon="120.543995"/><PT OrderNo="31" Lat="24.170772" Lon="120.542734"/><PT OrderNo="32" Lat="24.168877" Lon="120.542567"/><PT OrderNo="33" Lat="24.166173" Lon="120.542596"/><PT OrderNo="34" Lat="24.163078" Lon="120.543227"/><PT OrderNo="35" Lat="24.157832" Lon="120.544115"/><PT OrderNo="36" Lat="24.155049" Lon="120.544363"/><PT OrderNo="37" Lat="24.151447" Lon="120.545476"/><PT OrderNo="38" Lat="24.14807" Lon="120.546329"/><PT OrderNo="39" Lat="24.146076" Lon="120.546894"/><PT OrderNo="40" Lat="24.142162" Lon="120.548429"/><PT OrderNo="41" Lat="24.13865" Lon="120.550668"/><PT OrderNo="42" Lat="24.134595" Lon="120.553775"/><PT OrderNo="43" Lat="24.131308" Lon="120.55448"/><PT OrderNo="44" Lat="24.129585" Lon="120.555235"/><PT OrderNo="45" Lat="24.128771" Lon="120.55583"/><PT OrderNo="46" Lat="24.128076" Lon="120.556699"/><PT OrderNo="47" Lat="24.124542" Lon="120.562682"/><PT OrderNo="48" Lat="24.12325" Lon="120.564769"/><PT OrderNo="49" Lat="24.121452" Lon="120.569622"/><PT OrderNo="50" Lat="24.118595" Lon="120.576983"/><PT OrderNo="51" Lat="24.116302" Lon="120.583296"/><PT OrderNo="52" Lat="24.115707" Lon="120.584117"/><PT OrderNo="53" Lat="24.114874" Lon="120.584646"/><PT OrderNo="54" Lat="24.113949" Lon="120.585437"/><PT OrderNo="55" Lat="24.113532" Lon="120.586076"/><PT OrderNo="56" Lat="24.113161" Lon="120.587326"/><PT OrderNo="57" Lat="24.113573" Lon="120.590097"/><PT OrderNo="58" Lat="24.113571" Lon="120.591576"/><PT OrderNo="59" Lat="24.113309" Lon="120.592579"/><PT OrderNo="60" Lat="24.111376" Lon="120.598552"/><PT OrderNo="61" Lat="24.109923" Lon="120.602957"/><PT OrderNo="62" Lat="24.108123" Lon="120.608592"/><PT OrderNo="63" Lat="24.107568" Lon="120.611193"/><PT OrderNo="64" Lat="24.110662" Lon="120.611579"/><PT OrderNo="65" Lat="24.11264" Lon="120.61173"/><PT OrderNo="66" Lat="24.113776" Lon="120.610785"/><PT OrderNo="67" Lat="24.115519" Lon="120.61291"/><PT OrderNo="68" Lat="24.114031" Lon="120.614262"/><PT OrderNo="69" Lat="24.113972" Lon="120.615721"/><PT OrderNo="70" Lat="24.111818" Lon="120.615592"/><PT OrderNo="71" Lat="24.111534" Lon="120.618467"/><PT OrderNo="72" Lat="24.106784" Lon="120.614111"/><PT OrderNo="73" Lat="24.105853" Lon="120.616194"/><PT OrderNo="74" Lat="24.106446" Lon="120.618649"/><PT OrderNo="75" Lat="24.106565" Lon="120.61934"/><PT OrderNo="76" Lat="24.106545" Lon="120.619968"/><PT OrderNo="77" Lat="24.106291" Lon="120.623921"/><PT OrderNo="78" Lat="24.106198" Lon="120.625368"/><PT OrderNo="79" Lat="24.105609" Lon="120.628756"/><PT OrderNo="80" Lat="24.105174" Lon="120.631822"/><PT OrderNo="81" Lat="24.106742" Lon="120.634967"/><PT OrderNo="82" Lat="24.107531" Lon="120.637274"/><PT OrderNo="83" Lat="24.108406" Lon="120.64008"/><PT OrderNo="84" Lat="24.109571" Lon="120.643933"/><PT OrderNo="85" Lat="24.111393" Lon="120.649368"/><PT OrderNo="86" Lat="24.112175" Lon="120.651142"/><PT OrderNo="87" Lat="24.113024" Lon="120.652642"/><PT OrderNo="88" Lat="24.115067" Lon="120.65525"/><PT OrderNo="89" Lat="24.11742" Lon="120.658168"/><PT OrderNo="90" Lat="24.118552" Lon="120.659202"/><PT OrderNo="91" Lat="24.120145" Lon="120.66037"/><PT OrderNo="92" Lat="24.124517" Lon="120.663715"/><PT OrderNo="93" Lat="24.126391" Lon="120.665154"/><PT OrderNo="94" Lat="24.127298" Lon="120.666202"/><PT OrderNo="95" Lat="24.127808" Lon="120.667113"/><PT OrderNo="96" Lat="24.12981" Lon="120.671928"/><PT OrderNo="97" Lat="24.132372" Lon="120.677967"/><PT OrderNo="98" Lat="24.13439" Lon="120.682999"/><PT OrderNo="99" Lat="24.135852" Lon="120.682258"/><PT OrderNo="100" Lat="24.136785" Lon="120.684229"/><PT OrderNo="101" Lat="24.137355" Lon="120.68455"/><PT OrderNo="102" Lat="24.137701" Lon="120.684928"/><PT OrderNo="103" Lat="24.138384" Lon="120.685646"/><PT OrderNo="104" Lat="24.139169" Lon="120.684734"/><PT OrderNo="105" Lat="24.139549" Lon="120.685531"/></Route>
</Routes></BusDynInfo>