<?xml version="1.0" encoding="UTF-8" standalone="yes"?>
<BusDynInfo><EssentialInfo><Location><name>TCBUS</name><CenterName>Maxwin</CenterName></Location><UpdateTime>2014-12-20 07:48:53</UpdateTime><CoordinateSystem/></EssentialInfo>
<BusInfo><Stop Id="0135" routeId="91延" nameZh="臺中航空站" seqNo="1" pgp="0" terminal="0" districtId="1" GoBack="1" latitude="24.25377" longitude="120.59911" inDis="50" outDis="50" oid="05E0141E5EA64A7095C8E5548AB79BA5" /><Stop Id="5381" routeId="91延" nameZh="西勢十巷口" seqNo="2" pgp="0" terminal="0" districtId="1" GoBack="1" latitude="24.25557" longitude="120.60003" inDis="50" outDis="50" oid="312172944" /><Stop Id="3295" routeId="91延" nameZh="澔明公司" seqNo="3" pgp="0" terminal="0" districtId="1" GoBack="1" latitude="24.26215" longitude="120.60402" inDis="50" outDis="50" oid="14881" /><Stop Id="2223" routeId="91延" nameZh="吳厝里" seqNo="4" pgp="0" terminal="0" districtId="1" GoBack="1" latitude="24.2666" longitude="120.60631" inDis="50" outDis="50" oid="318972699" /><Stop Id="3434" routeId="91延" nameZh="新興社區" seqNo="5" pgp="0" terminal="0" districtId="1" GoBack="1" latitude="24.26934" longitude="120.60769" inDis="50" outDis="50" oid="318973124" /><Stop Id="3119" routeId="91延" nameZh="頂吳厝里" seqNo="6" pgp="0" terminal="0" districtId="1" GoBack="1" latitude="24.27616" longitude="120.61116" inDis="50" outDis="50" oid="318972695" /><Stop Id="4955" routeId="91延" nameZh="許厝寮" seqNo="7" pgp="0" terminal="0" districtId="1" GoBack="1" latitude="24.27944" longitude="120.61289" inDis="50" outDis="50" oid="318972693" /><Stop Id="1203" routeId="91延" nameZh="下楊厝里" seqNo="8" pgp="0" terminal="0" districtId="1" GoBack="1" latitude="24.28594" longitude="120.6133" inDis="50" outDis="50" oid="318972691" /><Stop Id="3448" routeId="91延" nameZh="楊厝里" seqNo="9" pgp="0" terminal="0" districtId="1" GoBack="1" latitude="24.28907" longitude="120.61558" inDis="50" outDis="50" oid="318972689" /><Stop Id="2807" routeId="91延" nameZh="海風里" seqNo="10" pgp="0" terminal="0" districtId="1" GoBack="1" latitude="24.29252" longitude="120.61939" inDis="50" outDis="50" oid="318972687" /><Stop Id="2271" routeId="91延" nameZh="良逸公司" seqNo="11" pgp="0" terminal="0" districtId="1" GoBack="1" latitude="24.29249" longitude="120.62546" inDis="50" outDis="50" oid="318972685" /><Stop Id="1215" routeId="91延" nameZh="下舊庄" seqNo="12" pgp="0" terminal="0" districtId="1" GoBack="1" latitude="24.29275" longitude="120.63047" inDis="50" outDis="50" oid="318972683" /><Stop Id="3918" routeId="91延" nameZh="舊庄" seqNo="13" pgp="0" terminal="0" districtId="1" GoBack="1" latitude="24.29185" longitude="120.63278" inDis="50" outDis="50" oid="318972681" /><Stop Id="3180" routeId="91延" nameZh="頂舊庄" seqNo="14" pgp="0" terminal="0" districtId="1" GoBack="1" latitude="24.2898" longitude="120.63516" inDis="50" outDis="50" oid="318972679" /><Stop Id="1948" routeId="91延" nameZh="永進公司" seqNo="15" pgp="0" terminal="0" districtId="1" GoBack="1" latitude="24.28672" longitude="120.64146" inDis="50" outDis="50" oid="318972677" /><Stop Id="3062" routeId="91延" nameZh="庄尾" seqNo="16" pgp="0" terminal="0" districtId="1" GoBack="1" latitude="24.28265" longitude="120.64949" inDis="50" outDis="50" oid="12266" /><Stop Id="3418" routeId="91延" nameZh="新庄車庫" seqNo="17" pgp="0" terminal="0" districtId="1" GoBack="1" latitude="24.28102" longitude="120.65244" inDis="50" outDis="50" oid="318972673" /><Stop Id="3415" routeId="91延" nameZh="新庄" seqNo="18" pgp="0" terminal="0" districtId="1" GoBack="1" latitude="24.28033" longitude="120.65427" inDis="50" outDis="50" oid="318972671" /><Stop Id="3660" routeId="91延" nameZh="福德祠" seqNo="19" pgp="0" terminal="0" districtId="1" GoBack="1" latitude="24.27786" longitude="120.65796" inDis="50" outDis="50" oid="319728591" /><Stop Id="3121" routeId="91延" nameZh="頂車站" seqNo="20" pgp="0" terminal="0" districtId="1" GoBack="1" latitude="24.27418" longitude="120.65903" inDis="50" outDis="50" oid="318972667" /><Stop Id="2095" routeId="91延" nameZh="圳堵" seqNo="21" pgp="0" terminal="0" districtId="1" GoBack="1" latitude="24.26876" longitude="120.65646" inDis="50" outDis="50" oid="319728592" /><Stop Id="4755" routeId="91延" nameZh="圳堵里口" seqNo="22" pgp="0" terminal="0" districtId="1" GoBack="1" latitude="24.26864" longitude="120.65642" inDis="50" outDis="50" oid="318972663" /><Stop Id="3111" routeId="91延" nameZh="頂圳前" seqNo="23" pgp="0" terminal="0" districtId="1" GoBack="1" latitude="24.26674" longitude="120.65676" inDis="50" outDis="50" oid="319728593" /><Stop Id="2094" routeId="91延" nameZh="圳前里" seqNo="24" pgp="0" terminal="0" districtId="1" GoBack="1" latitude="24.26399" longitude="120.65766" inDis="50" outDis="50" oid="318972659" /><Stop Id="4962" routeId="91延" nameZh="神圳國中" seqNo="25" pgp="0" terminal="0" districtId="1" GoBack="1" latitude="24.26062" longitude="120.65861" inDis="50" outDis="50" oid="318972657" /><Stop Id="4445" routeId="91延" nameZh="中正中山路口" seqNo="26" pgp="0" terminal="0" districtId="1" GoBack="1" latitude="24.25842" longitude="120.65605" inDis="50" outDis="50" oid="13808" /><Stop Id="2835" routeId="91延" nameZh="神岡" seqNo="27" pgp="0" terminal="0" districtId="1" GoBack="1" latitude="24.25703" longitude="120.6593" inDis="50" outDis="50" oid="318972653" /><Stop Id="2837" routeId="91延" nameZh="神岡區公所" seqNo="28" pgp="0" terminal="0" districtId="1" GoBack="1" latitude="24.25771" longitude="120.66141" inDis="50" outDis="50" oid="318972651" /><Stop Id="3066" routeId="91延" nameZh="庄頭" seqNo="29" pgp="0" terminal="0" districtId="1" GoBack="1" latitude="24.25812" longitude="120.66294" inDis="50" outDis="50" oid="318972649" /><Stop Id="1783" routeId="91延" nameZh="北庄" seqNo="30" pgp="0" terminal="0" districtId="1" GoBack="1" latitude="24.25732" longitude="120.66832" inDis="50" outDis="50" oid="318972647" /><Stop Id="3460" routeId="91延" nameZh="中山溝心路口" seqNo="31" pgp="0" terminal="0" districtId="1" GoBack="1" latitude="24.25521" longitude="120.67224" inDis="50" outDis="50" oid="318972645" /><Stop Id="3556" routeId="91延" nameZh="電信局" seqNo="32" pgp="0" terminal="0" districtId="1" GoBack="1" latitude="24.25294" longitude="120.67387" inDis="50" outDis="50" oid="318972643" /><Stop Id="3655" routeId="91延" nameZh="福華公司" seqNo="33" pgp="0" terminal="0" districtId="1" GoBack="1" latitude="24.25099" longitude="120.67622" inDis="50" outDis="50" oid="318972641" /><Stop Id="3656" routeId="91延" nameZh="福隆新村" seqNo="34" pgp="0" terminal="0" districtId="1" GoBack="1" latitude="24.24901" longitude="120.67946" inDis="50" outDis="50" oid="318972639" /><Stop Id="2836" routeId="91延" nameZh="神岡國中" seqNo="35" pgp="0" terminal="0" districtId="1" GoBack="1" latitude="24.24731" longitude="120.68146" inDis="50" outDis="50" oid="318972637" /><Stop Id="2486" routeId="91延" nameZh="社口" seqNo="36" pgp="0" terminal="0" districtId="1" GoBack="1" latitude="24.24668" longitude="120.68563" inDis="50" outDis="50" oid="318972635" /><Stop Id="2700" routeId="91延" nameZh="紅瓦厝口" seqNo="37" pgp="0" terminal="0" districtId="1" GoBack="1" latitude="24.2476" longitude="120.6896" inDis="50" outDis="50" oid="318972633" /><Stop Id="2993" routeId="91延" nameZh="望寮" seqNo="38" pgp="0" terminal="0" districtId="1" GoBack="1" latitude="24.24841" longitude="120.69323" inDis="50" outDis="50" oid="318972631" /><Stop Id="5438" routeId="91延" nameZh="岸裡國小" seqNo="39" pgp="0" terminal="0" districtId="1" GoBack="1" latitude="24.2487" longitude="120.698" inDis="50" outDis="50" oid="318972629" /><Stop Id="4498" routeId="91延" nameZh="臺豐社區" seqNo="40" pgp="0" terminal="0" districtId="1" GoBack="1" latitude="24.249" longitude="120.70003" inDis="50" outDis="50" oid="318972627" /><Stop Id="2489" routeId="91延" nameZh="社皮鐵路巷" seqNo="41" pgp="0" terminal="0" districtId="1" GoBack="1" latitude="24.24951" longitude="120.70229" inDis="50" outDis="50" oid="318972625" /><Stop Id="2349" routeId="91延" nameZh="忠勤新村" seqNo="42" pgp="0" terminal="0" districtId="1" GoBack="1" latitude="24.24962" longitude="120.70434" inDis="50" outDis="50" oid="318972623" /><Stop Id="1065" routeId="91延" nameZh="三光新村" seqNo="43" pgp="0" terminal="0" districtId="1" GoBack="1" latitude="24.24999" longitude="120.70672" inDis="50" outDis="50" oid="318972621" /><Stop Id="4448" routeId="91延" nameZh="中正圓環西路口" seqNo="44" pgp="0" terminal="0" districtId="1" GoBack="1" latitude="24.25039" longitude="120.70963" inDis="50" outDis="50" oid="318972619" /><Stop Id="3357" routeId="91延" nameZh="慈龍寺" seqNo="45" pgp="0" terminal="0" districtId="1" GoBack="1" latitude="24.25079" longitude="120.712" inDis="50" outDis="50" oid="318972617" /><Stop Id="3939" routeId="91延" nameZh="豐原郵局" seqNo="46" pgp="0" terminal="0" districtId="1" GoBack="1" latitude="24.25136" longitude="120.71526" inDis="50" outDis="50" oid="318972615" /><Stop Id="3343" routeId="91延" nameZh="媽祖廟" seqNo="47" pgp="0" terminal="0" districtId="1" GoBack="1" latitude="24.25202" longitude="120.71865" inDis="50" outDis="50" oid="306625599" /><Stop Id="2309" routeId="91延" nameZh="和平街" seqNo="48" pgp="0" terminal="0" districtId="1" GoBack="1" latitude="24.25208" longitude="120.7198" inDis="50" outDis="50" oid="5836" /><Stop Id="3935" routeId="91延" nameZh="豐原" seqNo="49" pgp="0" terminal="0" districtId="1" GoBack="1" latitude="24.25388" longitude="120.72188" inDis="50" outDis="50" oid="13338" /><Stop Id="3157" routeId="91延" nameZh="頂街" seqNo="50" pgp="0" terminal="0" districtId="1" GoBack="1" latitude="24.25234" longitude="120.72123" inDis="50" outDis="50" oid="13863" /><Stop Id="4203" routeId="91延" nameZh="新都酒店" seqNo="51" pgp="0" terminal="0" districtId="1" GoBack="1" latitude="24.25221" longitude="120.72394" inDis="50" outDis="50" oid="13610" /><Stop Id="4408" routeId="91延" nameZh="豐原老人會館" seqNo="52" pgp="0" terminal="0" districtId="1" GoBack="1" latitude="24.25219" longitude="120.72603" inDis="50" outDis="50" oid="13611" /><Stop Id="4457" routeId="91延" nameZh="向陽圓環東路口" seqNo="53" pgp="0" terminal="0" districtId="1" GoBack="1" latitude="24.25133" longitude="120.72786" inDis="50" outDis="50" oid="13812" /><Stop Id="5544" routeId="91延" nameZh="葫蘆墩文化中心" seqNo="54" pgp="0" terminal="0" districtId="1" GoBack="1" latitude="24.25299" longitude="120.72976" inDis="50" outDis="50" oid="316462696" /><Stop Id="4478" routeId="91延" nameZh="圓環東水源路口" seqNo="55" pgp="0" terminal="0" districtId="1" GoBack="1" latitude="24.25577" longitude="120.72983" inDis="50" outDis="50" oid="13820" /><Stop Id="4407" routeId="91延" nameZh="永豐原紙廠" seqNo="56" pgp="0" terminal="0" districtId="1" GoBack="1" latitude="24.2587" longitude="120.73227" inDis="50" outDis="50" oid="13615" /><Stop Id="2843" routeId="91延" nameZh="翁子" seqNo="57" pgp="0" terminal="0" districtId="1" GoBack="1" latitude="24.26058" longitude="120.73593" inDis="50" outDis="50" oid="13616" /><Stop Id="2844" routeId="91延" nameZh="翁子保養場" seqNo="58" pgp="0" terminal="0" districtId="1" GoBack="1" latitude="24.26226" longitude="120.73947" inDis="50" outDis="50" oid="13617" /><Stop Id="2845" routeId="91延" nameZh="翁子國小" seqNo="59" pgp="0" terminal="0" districtId="1" GoBack="1" latitude="24.2638" longitude="120.74277" inDis="50" outDis="50" oid="13618" /><Stop Id="1806" routeId="91延" nameZh="半張" seqNo="60" pgp="0" terminal="0" districtId="1" GoBack="1" latitude="24.26517" longitude="120.74564" inDis="50" outDis="50" oid="13619" /><Stop Id="4490" routeId="91延" nameZh="豐勢國豐路口" seqNo="61" pgp="0" terminal="0" districtId="1" GoBack="1" latitude="24.2678" longitude="120.74924" inDis="50" outDis="50" oid="13830" /><Stop Id="4412" routeId="91延" nameZh="國家教育研究院" seqNo="62" pgp="0" terminal="0" districtId="1" GoBack="1" latitude="24.27084" longitude="120.75175" inDis="50" outDis="50" oid="13621" /><Stop Id="2128" routeId="91延" nameZh="朴子口" seqNo="63" pgp="0" terminal="0" districtId="1" GoBack="1" latitude="24.27345" longitude="120.75398" inDis="50" outDis="50" oid="13622" /><Stop Id="4454" routeId="91延" nameZh="民安" seqNo="64" pgp="0" terminal="0" districtId="1" GoBack="1" latitude="24.27507" longitude="120.75652" inDis="50" outDis="50" oid="13796" /><Stop Id="2947" routeId="91延" nameZh="埤頭" seqNo="65" pgp="0" terminal="0" districtId="1" GoBack="1" latitude="24.27657" longitude="120.75916" inDis="50" outDis="50" oid="13624" /><Stop Id="2005" routeId="91延" nameZh="石岡水壩" seqNo="66" pgp="0" terminal="0" districtId="1" GoBack="1" latitude="24.27812" longitude="120.76675" inDis="50" outDis="50" oid="13625" /><Stop Id="2337" routeId="91延" nameZh="岡尾" seqNo="67" pgp="0" terminal="0" districtId="1" GoBack="1" latitude="24.27755" longitude="120.7719" inDis="50" outDis="50" oid="13626" /><Stop Id="2004" routeId="91延" nameZh="石岡" seqNo="68" pgp="0" terminal="0" districtId="1" GoBack="1" latitude="24.27653" longitude="120.77635" inDis="50" outDis="50" oid="13627" /><Stop Id="4456" routeId="91延" nameZh="石岡區公所" seqNo="69" pgp="0" terminal="0" districtId="1" GoBack="1" latitude="24.27492" longitude="120.78075" inDis="50" outDis="50" oid="13628" /><Stop Id="0992" routeId="91延" nameZh="九房厝" seqNo="70" pgp="0" terminal="0" districtId="1" GoBack="1" latitude="24.27447" longitude="120.78428" inDis="50" outDis="50" oid="13629" /><Stop Id="2983" routeId="91延" nameZh="情人木橋" seqNo="71" pgp="0" terminal="0" districtId="1" GoBack="1" latitude="24.27386" longitude="120.78874" inDis="50" outDis="50" oid="13630" /><Stop Id="4495" routeId="91延" nameZh="萬仙萬華街口" seqNo="72" pgp="0" terminal="0" districtId="1" GoBack="1" latitude="24.27123" longitude="120.79089" inDis="50" outDis="50" oid="13822" /><Stop Id="3746" routeId="91延" nameZh="盤安橋" seqNo="73" pgp="0" terminal="0" districtId="1" GoBack="1" latitude="24.26861" longitude="120.79115" inDis="50" outDis="50" oid="319728594" /><Stop Id="4512" routeId="91延" nameZh="親水緣" seqNo="74" pgp="0" terminal="0" districtId="1" GoBack="1" latitude="24.26254" longitude="120.79752" inDis="50" outDis="50" oid="13828" /><Stop Id="4461" routeId="91延" nameZh="協園" seqNo="75" pgp="0" terminal="0" districtId="1" GoBack="1" latitude="24.25984" longitude="120.79948" inDis="50" outDis="50" oid="13814" /><Stop Id="1394" routeId="91延" nameZh="山頂" seqNo="76" pgp="0" terminal="0" districtId="1" GoBack="1" latitude="24.25547" longitude="120.80698" inDis="50" outDis="50" oid="13720" /><Stop Id="3557" routeId="91延" nameZh="電信局前" seqNo="77" pgp="0" terminal="0" districtId="1" GoBack="1" latitude="24.25384" longitude="120.80756" inDis="50" outDis="50" oid="13721" /><Stop Id="1438" routeId="91延" nameZh="中正里" seqNo="78" pgp="0" terminal="0" districtId="1" GoBack="1" latitude="24.25055" longitude="120.80877" inDis="50" outDis="50" oid="13722" /><Stop Id="0011" routeId="91延" nameZh="郵局" seqNo="79" pgp="0" terminal="0" districtId="1" GoBack="1" latitude="24.24772" longitude="120.80868" inDis="50" outDis="50" oid="13723" /><Stop Id="1199" routeId="91延" nameZh="下新社" seqNo="80" pgp="0" terminal="0" districtId="1" GoBack="1" latitude="24.24637" longitude="120.80832" inDis="50" outDis="50" oid="13724" /><Stop Id="3398" routeId="91延" nameZh="新社" seqNo="81" pgp="0" terminal="0" districtId="1" GoBack="1" latitude="24.24458" longitude="120.80835" inDis="50" outDis="50" oid="13725" /><Stop Id="3162" routeId="91延" nameZh="頂新社" seqNo="82" pgp="0" terminal="0" districtId="1" GoBack="1" latitude="24.24262" longitude="120.80769" inDis="50" outDis="50" oid="13726" /><Stop Id="3401" routeId="91延" nameZh="新社新村" seqNo="83" pgp="0" terminal="0" districtId="1" GoBack="1" latitude="24.23916" longitude="120.80659" inDis="50" outDis="50" oid="13727" /><Stop Id="3400" routeId="91延" nameZh="新社高中" seqNo="84" pgp="0" terminal="0" districtId="1" GoBack="1" latitude="24.23715" longitude="120.80571" inDis="50" outDis="50" oid="13728" /><Stop Id="3228" routeId="91延" nameZh="復興社區" seqNo="85" pgp="0" terminal="0" districtId="1" GoBack="1" latitude="24.23582" longitude="120.80451" inDis="50" outDis="50" oid="6335" /><Stop Id="3679" routeId="91延" nameZh="種苗繁殖場" seqNo="86" pgp="0" terminal="0" districtId="1" GoBack="1" latitude="24.23041" longitude="120.80341" inDis="50" outDis="50" oid="6571" /><Stop Id="1318" routeId="91延" nameZh="大南" seqNo="87" pgp="0" terminal="0" districtId="1" GoBack="1" latitude="24.22922" longitude="120.79961" inDis="50" outDis="50" oid="5239" /><Stop Id="2356" routeId="91延" nameZh="內觀中心" seqNo="88" pgp="0" terminal="0" districtId="1" GoBack="1" latitude="24.22815" longitude="120.79874" inDis="50" outDis="50" oid="5864" /><Stop Id="3586" routeId="91延" nameZh="廖厝" seqNo="89" pgp="0" terminal="0" districtId="1" GoBack="1" latitude="24.22637" longitude="120.79749" inDis="50" outDis="50" oid="6530" /><Stop Id="1720" routeId="91延" nameZh="水頭" seqNo="90" pgp="0" terminal="0" districtId="1" GoBack="1" latitude="24.22431" longitude="120.79585" inDis="50" outDis="50" oid="5490" /><Stop Id="2940" routeId="91延" nameZh="國隆社區" seqNo="91" pgp="0" terminal="0" districtId="1" GoBack="1" latitude="24.22204" longitude="120.79363" inDis="50" outDis="50" oid="6181" /><Stop Id="2892" routeId="91延" nameZh="馬力埔" seqNo="92" pgp="0" terminal="0" districtId="1" GoBack="1" latitude="24.22078" longitude="120.7931" inDis="50" outDis="50" oid="6159" /><Stop Id="2675" routeId="91延" nameZh="活動中心" seqNo="93" pgp="0" terminal="0" districtId="1" GoBack="1" latitude="24.219" longitude="120.79235" inDis="50" outDis="50" oid="6036" /><Stop Id="2987" routeId="91延" nameZh="教堂前" seqNo="94" pgp="0" terminal="0" districtId="1" GoBack="1" latitude="24.21843" longitude="120.79421" inDis="50" outDis="50" oid="6199" /><Stop Id="3363" routeId="91延" nameZh="新二村" seqNo="95" pgp="0" terminal="0" districtId="1" GoBack="1" latitude="24.21843" longitude="120.79592" inDis="50" outDis="50" oid="6409" /><Stop Id="3082" routeId="91延" nameZh="陳厝" seqNo="96" pgp="0" terminal="0" districtId="1" GoBack="1" latitude="24.21432" longitude="120.79589" inDis="50" outDis="50" oid="6273" /><Stop Id="1123" routeId="91延" nameZh="下中興嶺" seqNo="97" pgp="0" terminal="0" districtId="1" GoBack="1" latitude="24.21135" longitude="120.79585" inDis="50" outDis="50" oid="5108" /><Stop Id="3885" routeId="91延" nameZh="營區前" seqNo="98" pgp="0" terminal="0" districtId="1" GoBack="1" latitude="24.20752" longitude="120.79448" inDis="50" outDis="50" oid="6668" /><Stop Id="0437" routeId="91延" nameZh="中興嶺" seqNo="99" pgp="0" terminal="0" districtId="1" GoBack="1" latitude="24.20579" longitude="120.79406" inDis="50" outDis="50" oid="6753" /><Stop Id="4756" routeId="91延" nameZh="中興嶺停車場" seqNo="100" pgp="0" terminal="0" districtId="1" GoBack="1" latitude="24.20427" longitude="120.79627" inDis="50" outDis="50" oid="307119934" /><Stop Id="4756" routeId="91延" nameZh="中興嶺停車場" seqNo="1" pgp="0" terminal="0" districtId="1" GoBack="2" latitude="24.20427" longitude="120.79627" inDis="50" outDis="50" oid="307119934" /><Stop Id="0437" routeId="91延" nameZh="中興嶺" seqNo="2" pgp="0" terminal="0" districtId="1" GoBack="2" latitude="24.20579" longitude="120.79406" inDis="50" outDis="50" oid="6753" /><Stop Id="3885" routeId="91延" nameZh="營區前" seqNo="3" pgp="0" terminal="0" districtId="1" GoBack="2" latitude="24.20752" longitude="120.79448" inDis="50" outDis="50" oid="6668" /><Stop Id="1123" routeId="91延" nameZh="下中興嶺" seqNo="4" pgp="0" terminal="0" districtId="1" GoBack="2" latitude="24.21135" longitude="120.79585" inDis="50" outDis="50" oid="5108" /><Stop Id="3082" routeId="91延" nameZh="陳厝" seqNo="5" pgp="0" terminal="0" districtId="1" GoBack="2" latitude="24.21432" longitude="120.79589" inDis="50" outDis="50" oid="6273" /><Stop Id="3363" routeId="91延" nameZh="新二村" seqNo="6" pgp="0" terminal="0" districtId="1" GoBack="2" latitude="24.21843" longitude="120.79592" inDis="50" outDis="50" oid="6409" /><Stop Id="2987" routeId="91延" nameZh="教堂前" seqNo="7" pgp="0" terminal="0" districtId="1" GoBack="2" latitude="24.21843" longitude="120.79421" inDis="50" outDis="50" oid="6199" /><Stop Id="2675" routeId="91延" nameZh="活動中心" seqNo="8" pgp="0" terminal="0" districtId="1" GoBack="2" latitude="24.219" longitude="120.79235" inDis="50" outDis="50" oid="6036" /><Stop Id="2892" routeId="91延" nameZh="馬力埔" seqNo="9" pgp="0" terminal="0" districtId="1" GoBack="2" latitude="24.22078" longitude="120.7931" inDis="50" outDis="50" oid="6159" /><Stop Id="2940" routeId="91延" nameZh="國隆社區" seqNo="10" pgp="0" terminal="0" districtId="1" GoBack="2" latitude="24.22204" longitude="120.79363" inDis="50" outDis="50" oid="6181" /><Stop Id="1720" routeId="91延" nameZh="水頭" seqNo="11" pgp="0" terminal="0" districtId="1" GoBack="2" latitude="24.22431" longitude="120.79585" inDis="50" outDis="50" oid="5490" /><Stop Id="3586" routeId="91延" nameZh="廖厝" seqNo="12" pgp="0" terminal="0" districtId="1" GoBack="2" latitude="24.22637" longitude="120.79749" inDis="50" outDis="50" oid="6530" /><Stop Id="2356" routeId="91延" nameZh="內觀中心" seqNo="13" pgp="0" terminal="0" districtId="1" GoBack="2" latitude="24.22815" longitude="120.79874" inDis="50" outDis="50" oid="5864" /><Stop Id="1318" routeId="91延" nameZh="大南" seqNo="14" pgp="0" terminal="0" districtId="1" GoBack="2" latitude="24.22922" longitude="120.79961" inDis="50" outDis="50" oid="5239" /><Stop Id="3679" routeId="91延" nameZh="種苗繁殖場" seqNo="15" pgp="0" terminal="0" districtId="1" GoBack="2" latitude="24.23041" longitude="120.80341" inDis="50" outDis="50" oid="6571" /><Stop Id="3228" routeId="91延" nameZh="復興社區" seqNo="16" pgp="0" terminal="0" districtId="1" GoBack="2" latitude="24.23582" longitude="120.80451" inDis="50" outDis="50" oid="6335" /><Stop Id="3400" routeId="91延" nameZh="新社高中" seqNo="17" pgp="0" terminal="0" districtId="1" GoBack="2" latitude="24.23715" longitude="120.80571" inDis="50" outDis="50" oid="13728" /><Stop Id="3401" routeId="91延" nameZh="新社新村" seqNo="18" pgp="0" terminal="0" districtId="1" GoBack="2" latitude="24.23916" longitude="120.80659" inDis="50" outDis="50" oid="13727" /><Stop Id="3162" routeId="91延" nameZh="頂新社" seqNo="19" pgp="0" terminal="0" districtId="1" GoBack="2" latitude="24.24262" longitude="120.80769" inDis="50" outDis="50" oid="13726" /><Stop Id="3398" routeId="91延" nameZh="新社" seqNo="20" pgp="0" terminal="0" districtId="1" GoBack="2" latitude="24.24458" longitude="120.80835" inDis="50" outDis="50" oid="13725" /><Stop Id="1199" routeId="91延" nameZh="下新社" seqNo="21" pgp="0" terminal="0" districtId="1" GoBack="2" latitude="24.24637" longitude="120.80832" inDis="50" outDis="50" oid="13724" /><Stop Id="0011" routeId="91延" nameZh="郵局" seqNo="22" pgp="0" terminal="0" districtId="1" GoBack="2" latitude="24.24772" longitude="120.80868" inDis="50" outDis="50" oid="13723" /><Stop Id="1438" routeId="91延" nameZh="中正里" seqNo="23" pgp="0" terminal="0" districtId="1" GoBack="2" latitude="24.25055" longitude="120.80877" inDis="50" outDis="50" oid="13722" /><Stop Id="3557" routeId="91延" nameZh="電信局前" seqNo="24" pgp="0" terminal="0" districtId="1" GoBack="2" latitude="24.25384" longitude="120.80756" inDis="50" outDis="50" oid="13721" /><Stop Id="1394" routeId="91延" nameZh="山頂" seqNo="25" pgp="0" terminal="0" districtId="1" GoBack="2" latitude="24.25547" longitude="120.80698" inDis="50" outDis="50" oid="13720" /><Stop Id="4461" routeId="91延" nameZh="協園" seqNo="26" pgp="0" terminal="0" districtId="1" GoBack="2" latitude="24.25984" longitude="120.79948" inDis="50" outDis="50" oid="13814" /><Stop Id="4512" routeId="91延" nameZh="親水緣" seqNo="27" pgp="0" terminal="0" districtId="1" GoBack="2" latitude="24.26254" longitude="120.79752" inDis="50" outDis="50" oid="13828" /><Stop Id="3746" routeId="91延" nameZh="盤安橋" seqNo="28" pgp="0" terminal="0" districtId="1" GoBack="2" latitude="24.26861" longitude="120.79115" inDis="50" outDis="50" oid="319728594" /><Stop Id="4495" routeId="91延" nameZh="萬仙萬華街口" seqNo="30" pgp="0" terminal="0" districtId="1" GoBack="2" latitude="24.27123" longitude="120.79089" inDis="50" outDis="50" oid="13822" /><Stop Id="2983" routeId="91延" nameZh="情人木橋" seqNo="31" pgp="0" terminal="0" districtId="1" GoBack="2" latitude="24.27386" longitude="120.78874" inDis="50" outDis="50" oid="13630" /><Stop Id="0992" routeId="91延" nameZh="九房厝" seqNo="32" pgp="0" terminal="0" districtId="1" GoBack="2" latitude="24.27447" longitude="120.78428" inDis="50" outDis="50" oid="13629" /><Stop Id="4456" routeId="91延" nameZh="石岡區公所" seqNo="33" pgp="0" terminal="0" districtId="1" GoBack="2" latitude="24.27492" longitude="120.78075" inDis="50" outDis="50" oid="13628" /><Stop Id="2004" routeId="91延" nameZh="石岡" seqNo="34" pgp="0" terminal="0" districtId="1" GoBack="2" latitude="24.27653" longitude="120.77635" inDis="50" outDis="50" oid="13627" /><Stop Id="2337" routeId="91延" nameZh="岡尾" seqNo="35" pgp="0" terminal="0" districtId="1" GoBack="2" latitude="24.27755" longitude="120.7719" inDis="50" outDis="50" oid="13626" /><Stop Id="2005" routeId="91延" nameZh="石岡水壩" seqNo="36" pgp="0" terminal="0" districtId="1" GoBack="2" latitude="24.27812" longitude="120.76675" inDis="50" outDis="50" oid="13625" /><Stop Id="2947" routeId="91延" nameZh="埤頭" seqNo="37" pgp="0" terminal="0" districtId="1" GoBack="2" latitude="24.27657" longitude="120.75916" inDis="50" outDis="50" oid="13624" /><Stop Id="4454" routeId="91延" nameZh="民安" seqNo="38" pgp="0" terminal="0" districtId="1" GoBack="2" latitude="24.27507" longitude="120.75652" inDis="50" outDis="50" oid="13796" /><Stop Id="2128" routeId="91延" nameZh="朴子口" seqNo="39" pgp="0" terminal="0" districtId="1" GoBack="2" latitude="24.27345" longitude="120.75398" inDis="50" outDis="50" oid="13622" /><Stop Id="4412" routeId="91延" nameZh="國家教育研究院" seqNo="40" pgp="0" terminal="0" districtId="1" GoBack="2" latitude="24.27084" longitude="120.75175" inDis="50" outDis="50" oid="13621" /><Stop Id="4490" routeId="91延" nameZh="豐勢國豐路口" seqNo="41" pgp="0" terminal="0" districtId="1" GoBack="2" latitude="24.2678" longitude="120.74924" inDis="50" outDis="50" oid="13830" /><Stop Id="1806" routeId="91延" nameZh="半張" seqNo="42" pgp="0" terminal="0" districtId="1" GoBack="2" latitude="24.26517" longitude="120.74564" inDis="50" outDis="50" oid="13619" /><Stop Id="2845" routeId="91延" nameZh="翁子國小" seqNo="43" pgp="0" terminal="0" districtId="1" GoBack="2" latitude="24.2638" longitude="120.74277" inDis="50" outDis="50" oid="13618" /><Stop Id="2844" routeId="91延" nameZh="翁子保養場" seqNo="44" pgp="0" terminal="0" districtId="1" GoBack="2" latitude="24.26226" longitude="120.73947" inDis="50" outDis="50" oid="13617" /><Stop Id="2843" routeId="91延" nameZh="翁子" seqNo="45" pgp="0" terminal="0" districtId="1" GoBack="2" latitude="24.26058" longitude="120.73593" inDis="50" outDis="50" oid="13616" /><Stop Id="4407" routeId="91延" nameZh="永豐原紙廠" seqNo="46" pgp="0" terminal="0" districtId="1" GoBack="2" latitude="24.2587" longitude="120.73227" inDis="50" outDis="50" oid="13615" /><Stop Id="4478" routeId="91延" nameZh="圓環東水源路口" seqNo="47" pgp="0" terminal="0" districtId="1" GoBack="2" latitude="24.25577" longitude="120.72983" inDis="50" outDis="50" oid="13820" /><Stop Id="5544" routeId="91延" nameZh="葫蘆墩文化中心" seqNo="48" pgp="0" terminal="0" districtId="1" GoBack="2" latitude="24.25299" longitude="120.72976" inDis="50" outDis="50" oid="316462696" /><Stop Id="4457" routeId="91延" nameZh="向陽圓環東路口" seqNo="49" pgp="0" terminal="0" districtId="1" GoBack="2" latitude="24.25133" longitude="120.72786" inDis="50" outDis="50" oid="13812" /><Stop Id="4408" routeId="91延" nameZh="豐原老人會館" seqNo="50" pgp="0" terminal="0" districtId="1" GoBack="2" latitude="24.25219" longitude="120.72603" inDis="50" outDis="50" oid="13611" /><Stop Id="4203" routeId="91延" nameZh="新都酒店" seqNo="51" pgp="0" terminal="0" districtId="1" GoBack="2" latitude="24.25221" longitude="120.72394" inDis="50" outDis="50" oid="13610" /><Stop Id="3157" routeId="91延" nameZh="頂街" seqNo="52" pgp="0" terminal="0" districtId="1" GoBack="2" latitude="24.25234" longitude="120.72123" inDis="50" outDis="50" oid="13863" /><Stop Id="3935" routeId="91延" nameZh="豐原" seqNo="53" pgp="0" terminal="0" districtId="1" GoBack="2" latitude="24.25388" longitude="120.72188" inDis="50" outDis="50" oid="13338" /><Stop Id="3343" routeId="91延" nameZh="媽祖廟" seqNo="54" pgp="0" terminal="0" districtId="1" GoBack="2" latitude="24.25202" longitude="120.71865" inDis="50" outDis="50" oid="306625599" /><Stop Id="3939" routeId="91延" nameZh="豐原郵局" seqNo="55" pgp="0" terminal="0" districtId="1" GoBack="2" latitude="24.25136" longitude="120.71526" inDis="50" outDis="50" oid="318972615" /><Stop Id="3357" routeId="91延" nameZh="慈龍寺" seqNo="56" pgp="0" terminal="0" districtId="1" GoBack="2" latitude="24.25079" longitude="120.712" inDis="50" outDis="50" oid="318972617" /><Stop Id="4448" routeId="91延" nameZh="中正圓環西路口" seqNo="57" pgp="0" terminal="0" districtId="1" GoBack="2" latitude="24.25039" longitude="120.70963" inDis="50" outDis="50" oid="318972619" /><Stop Id="1065" routeId="91延" nameZh="三光新村" seqNo="58" pgp="0" terminal="0" districtId="1" GoBack="2" latitude="24.24999" longitude="120.70672" inDis="50" outDis="50" oid="318972621" /><Stop Id="2349" routeId="91延" nameZh="忠勤新村" seqNo="59" pgp="0" terminal="0" districtId="1" GoBack="2" latitude="24.24962" longitude="120.70434" inDis="50" outDis="50" oid="318972623" /><Stop Id="2489" routeId="91延" nameZh="社皮鐵路巷" seqNo="60" pgp="0" terminal="0" districtId="1" GoBack="2" latitude="24.24951" longitude="120.70229" inDis="50" outDis="50" oid="318972625" /><Stop Id="4498" routeId="91延" nameZh="臺豐社區" seqNo="61" pgp="0" terminal="0" districtId="1" GoBack="2" latitude="24.249" longitude="120.70003" inDis="50" outDis="50" oid="318972627" /><Stop Id="5438" routeId="91延" nameZh="岸裡國小" seqNo="62" pgp="0" terminal="0" districtId="1" GoBack="2" latitude="24.2487" longitude="120.698" inDis="50" outDis="50" oid="318972629" /><Stop Id="2993" routeId="91延" nameZh="望寮" seqNo="63" pgp="0" terminal="0" districtId="1" GoBack="2" latitude="24.24841" longitude="120.69323" inDis="50" outDis="50" oid="318972631" /><Stop Id="2700" routeId="91延" nameZh="紅瓦厝口" seqNo="64" pgp="0" terminal="0" districtId="1" GoBack="2" latitude="24.2476" longitude="120.6896" inDis="50" outDis="50" oid="318972633" /><Stop Id="2486" routeId="91延" nameZh="社口" seqNo="65" pgp="0" terminal="0" districtId="1" GoBack="2" latitude="24.24668" longitude="120.68563" inDis="50" outDis="50" oid="318972635" /><Stop Id="2836" routeId="91延" nameZh="神岡國中" seqNo="66" pgp="0" terminal="0" districtId="1" GoBack="2" latitude="24.24731" longitude="120.68146" inDis="50" outDis="50" oid="318972637" /><Stop Id="3656" routeId="91延" nameZh="福隆新村" seqNo="67" pgp="0" terminal="0" districtId="1" GoBack="2" latitude="24.24901" longitude="120.67946" inDis="50" outDis="50" oid="318972639" /><Stop Id="3655" routeId="91延" nameZh="福華公司" seqNo="68" pgp="0" terminal="0" districtId="1" GoBack="2" latitude="24.25099" longitude="120.67622" inDis="50" outDis="50" oid="318972641" /><Stop Id="3556" routeId="91延" nameZh="電信局" seqNo="69" pgp="0" terminal="0" districtId="1" GoBack="2" latitude="24.25294" longitude="120.67387" inDis="50" outDis="50" oid="318972643" /><Stop Id="3460" routeId="91延" nameZh="中山溝心路口" seqNo="70" pgp="0" terminal="0" districtId="1" GoBack="2" latitude="24.25521" longitude="120.67224" inDis="50" outDis="50" oid="318972645" /><Stop Id="1783" routeId="91延" nameZh="北庄" seqNo="71" pgp="0" terminal="0" districtId="1" GoBack="2" latitude="24.25732" longitude="120.66832" inDis="50" outDis="50" oid="318972647" /><Stop Id="3066" routeId="91延" nameZh="庄頭" seqNo="72" pgp="0" terminal="0" districtId="1" GoBack="2" latitude="24.25812" longitude="120.66294" inDis="50" outDis="50" oid="318972649" /><Stop Id="2837" routeId="91延" nameZh="神岡區公所" seqNo="73" pgp="0" terminal="0" districtId="1" GoBack="2" latitude="24.25771" longitude="120.66141" inDis="50" outDis="50" oid="318972651" /><Stop Id="2835" routeId="91延" nameZh="神岡" seqNo="74" pgp="0" terminal="0" districtId="1" GoBack="2" latitude="24.25703" longitude="120.6593" inDis="50" outDis="50" oid="318972653" /><Stop Id="4445" routeId="91延" nameZh="中正中山路口" seqNo="75" pgp="0" terminal="0" districtId="1" GoBack="2" latitude="24.25842" longitude="120.65605" inDis="50" outDis="50" oid="13808" /><Stop Id="4962" routeId="91延" nameZh="神圳國中" seqNo="76" pgp="0" terminal="0" districtId="1" GoBack="2" latitude="24.26062" longitude="120.65861" inDis="50" outDis="50" oid="318972657" /><Stop Id="2094" routeId="91延" nameZh="圳前里" seqNo="77" pgp="0" terminal="0" districtId="1" GoBack="2" latitude="24.26399" longitude="120.65766" inDis="50" outDis="50" oid="318972659" /><Stop Id="3111" routeId="91延" nameZh="頂圳前" seqNo="78" pgp="0" terminal="0" districtId="1" GoBack="2" latitude="24.26674" longitude="120.65676" inDis="50" outDis="50" oid="319728593" /><Stop Id="4755" routeId="91延" nameZh="圳堵里口" seqNo="79" pgp="0" terminal="0" districtId="1" GoBack="2" latitude="24.26864" longitude="120.65642" inDis="50" outDis="50" oid="318972663" /><Stop Id="2095" routeId="91延" nameZh="圳堵" seqNo="80" pgp="0" terminal="0" districtId="1" GoBack="2" latitude="24.26876" longitude="120.65646" inDis="50" outDis="50" oid="319728592" /><Stop Id="3121" routeId="91延" nameZh="頂車站" seqNo="81" pgp="0" terminal="0" districtId="1" GoBack="2" latitude="24.27418" longitude="120.65903" inDis="50" outDis="50" oid="318972667" /><Stop Id="3660" routeId="91延" nameZh="福德祠" seqNo="82" pgp="0" terminal="0" districtId="1" GoBack="2" latitude="24.27786" longitude="120.65796" inDis="50" outDis="50" oid="319728591" /><Stop Id="3415" routeId="91延" nameZh="新庄" seqNo="83" pgp="0" terminal="0" districtId="1" GoBack="2" latitude="24.28033" longitude="120.65427" inDis="50" outDis="50" oid="318972671" /><Stop Id="3418" routeId="91延" nameZh="新庄車庫" seqNo="84" pgp="0" terminal="0" districtId="1" GoBack="2" latitude="24.28102" longitude="120.65244" inDis="50" outDis="50" oid="318972673" /><Stop Id="3062" routeId="91延" nameZh="庄尾" seqNo="85" pgp="0" terminal="0" districtId="1" GoBack="2" latitude="24.28265" longitude="120.64949" inDis="50" outDis="50" oid="12266" /><Stop Id="1948" routeId="91延" nameZh="永進公司" seqNo="86" pgp="0" terminal="0" districtId="1" GoBack="2" latitude="24.28672" longitude="120.64146" inDis="50" outDis="50" oid="318972677" /><Stop Id="3180" routeId="91延" nameZh="頂舊庄" seqNo="87" pgp="0" terminal="0" districtId="1" GoBack="2" latitude="24.2898" longitude="120.63516" inDis="50" outDis="50" oid="318972679" /><Stop Id="3918" routeId="91延" nameZh="舊庄" seqNo="88" pgp="0" terminal="0" districtId="1" GoBack="2" latitude="24.29185" longitude="120.63278" inDis="50" outDis="50" oid="318972681" /><Stop Id="1215" routeId="91延" nameZh="下舊庄" seqNo="89" pgp="0" terminal="0" districtId="1" GoBack="2" latitude="24.29275" longitude="120.63047" inDis="50" outDis="50" oid="318972683" /><Stop Id="2271" routeId="91延" nameZh="良逸公司" seqNo="90" pgp="0" terminal="0" districtId="1" GoBack="2" latitude="24.29249" longitude="120.62546" inDis="50" outDis="50" oid="318972685" /><Stop Id="2807" routeId="91延" nameZh="海風里" seqNo="91" pgp="0" terminal="0" districtId="1" GoBack="2" latitude="24.29252" longitude="120.61939" inDis="50" outDis="50" oid="318972687" /><Stop Id="3448" routeId="91延" nameZh="楊厝里" seqNo="92" pgp="0" terminal="0" districtId="1" GoBack="2" latitude="24.28907" longitude="120.61558" inDis="50" outDis="50" oid="318972689" /><Stop Id="1203" routeId="91延" nameZh="下楊厝里" seqNo="93" pgp="0" terminal="0" districtId="1" GoBack="2" latitude="24.28594" longitude="120.6133" inDis="50" outDis="50" oid="318972691" /><Stop Id="4955" routeId="91延" nameZh="許厝寮" seqNo="94" pgp="0" terminal="0" districtId="1" GoBack="2" latitude="24.27944" longitude="120.61289" inDis="50" outDis="50" oid="318972693" /><Stop Id="3119" routeId="91延" nameZh="頂吳厝里" seqNo="95" pgp="0" terminal="0" districtId="1" GoBack="2" latitude="24.27616" longitude="120.61116" inDis="50" outDis="50" oid="318972695" /><Stop Id="3434" routeId="91延" nameZh="新興社區" seqNo="96" pgp="0" terminal="0" districtId="1" GoBack="2" latitude="24.26934" longitude="120.60769" inDis="50" outDis="50" oid="318973124" /><Stop Id="2223" routeId="91延" nameZh="吳厝里" seqNo="97" pgp="0" terminal="0" districtId="1" GoBack="2" latitude="24.2666" longitude="120.60631" inDis="50" outDis="50" oid="318972699" /><Stop Id="3295" routeId="91延" nameZh="澔明公司" seqNo="98" pgp="0" terminal="0" districtId="1" GoBack="2" latitude="24.26215" longitude="120.60402" inDis="50" outDis="50" oid="14881" /><Stop Id="5381" routeId="91延" nameZh="西勢十巷口" seqNo="99" pgp="0" terminal="0" districtId="1" GoBack="2" latitude="24.25557" longitude="120.60003" inDis="50" outDis="50" oid="312172944" /><Stop Id="0135" routeId="91延" nameZh="臺中航空站" seqNo="100" pgp="0" terminal="0" districtId="1" GoBack="2" latitude="24.25377" longitude="120.59911" inDis="50" outDis="50" oid="05E0141E5EA64A7095C8E5548AB79BA5" /></BusInfo></BusDynInfo>