<?xml version="1.0" encoding="UTF-8" standalone="yes"?>
<BusDynInfo><EssentialInfo><Location><name>TCBUS</name><CenterName>Maxwin</CenterName></Location><UpdateTime>2014-12-20 07:27:57</UpdateTime><CoordinateSystem/></EssentialInfo>
<BusInfo><Stop Id="4399" routeId="26" nameZh="新民高中(三民路)" seqNo="1" pgp="0" terminal="0" districtId="1" GoBack="1" latitude="24.15641" longitude="120.68828" inDis="50" outDis="50" oid="3EE27BCBC4A3444D9EB7E73AC2F435C0" /><Stop Id="0934" routeId="26" nameZh="三民錦中街口" seqNo="2" pgp="0" terminal="0" districtId="1" GoBack="1" latitude="24.15528" longitude="120.68695" inDis="50" outDis="50" oid="0D7AF382298E449C9856AF45F92F27F9" /><Stop Id="0047" routeId="26" nameZh="一心市場" seqNo="3" pgp="0" terminal="0" districtId="1" GoBack="1" latitude="24.1542" longitude="120.68587" inDis="50" outDis="50" oid="F4B71140B9D244C68A570881F199A969" /><Stop Id="0046" routeId="26" nameZh="中友百貨" seqNo="4" pgp="0" terminal="0" districtId="1" GoBack="1" latitude="24.15255" longitude="120.68515" inDis="50" outDis="50" oid="A646F5AFA9F14D6883067DD2CC5CC06B" /><Stop Id="0045" routeId="26" nameZh="國立臺中科技大學" seqNo="5" pgp="0" terminal="0" districtId="1" GoBack="1" latitude="24.14959" longitude="120.68393" inDis="50" outDis="50" oid="CBF0469F09E240B0867F69500E48B9E5" /><Stop Id="4543" routeId="26" nameZh="臺中公園(三民路)" seqNo="6" pgp="0" terminal="0" districtId="1" GoBack="1" latitude="24.14526" longitude="120.68223" inDis="50" outDis="50" oid="6F81DDD56D3943B6AAF6E29FD6951FF6" /><Stop Id="5506" routeId="26" nameZh="光復國小(三民路)" seqNo="7" pgp="0" terminal="0" districtId="1" GoBack="1" latitude="24.14368" longitude="120.68091" inDis="50" outDis="50" oid="315386762" /><Stop Id="4609" routeId="26" nameZh="第二市場(三民路)" seqNo="8" pgp="0" terminal="0" districtId="1" GoBack="1" latitude="24.14268" longitude="120.68" inDis="50" outDis="50" oid="EE17AB29EF464F9CA084E8425184F6ED" /><Stop Id="5026" routeId="26" nameZh="美榮藥局" seqNo="9" pgp="0" terminal="0" districtId="1" GoBack="1" latitude="24.14131" longitude="120.67838" inDis="50" outDis="50" oid="309504377" /><Stop Id="0209" routeId="26" nameZh="臺中科大民生校區" seqNo="10" pgp="0" terminal="0" districtId="1" GoBack="1" latitude="24.139" longitude="120.67604" inDis="50" outDis="50" oid="10382" /><Stop Id="0210" routeId="26" nameZh="忠孝國小" seqNo="11" pgp="0" terminal="0" districtId="1" GoBack="1" latitude="24.13723" longitude="120.67406" inDis="50" outDis="50" oid="BDA20E5509C64110B298E9D9E91B449B" /><Stop Id="0673" routeId="26" nameZh="三民林森路口" seqNo="12" pgp="0" terminal="0" districtId="1" GoBack="1" latitude="24.13576" longitude="120.67258" inDis="50" outDis="50" oid="DB7285C989BA49C7A1D6B199B9C8929A" /><Stop Id="5661" routeId="26" nameZh="公館(三民路)" seqNo="13" pgp="0" terminal="0" districtId="1" GoBack="1" latitude="24.1329" longitude="120.66961" inDis="50" outDis="50" oid="C78046F3FF1E4164B7AFEBEDB87A98FA" /><Stop Id="0562" routeId="26" nameZh="永安市場" seqNo="14" pgp="0" terminal="0" districtId="1" GoBack="1" latitude="24.13217" longitude="120.66497" inDis="50" outDis="50" oid="7E2E9232B9924540A4CF9CB9A99E3BBF" /><Stop Id="4637" routeId="26" nameZh="南屯美村路口" seqNo="15" pgp="0" terminal="0" districtId="1" GoBack="1" latitude="24.13222" longitude="120.66207" inDis="50" outDis="50" oid="9AFF6D4F442F44179B4872EE997FBFF3" /><Stop Id="0935" routeId="26" nameZh="靜和醫院" seqNo="16" pgp="0" terminal="0" districtId="1" GoBack="1" latitude="24.13327" longitude="120.65976" inDis="50" outDis="50" oid="23D976C721DC4CFEBE538221BF59B314" /><Stop Id="0126" routeId="26" nameZh="崇倫國中(南屯路)" seqNo="17" pgp="0" terminal="0" districtId="1" GoBack="1" latitude="24.13378" longitude="120.65798" inDis="50" outDis="50" oid="4904019BCA5C476CA16E094B1D9FD87C" /><Stop Id="0348" routeId="26" nameZh="土庫" seqNo="18" pgp="0" terminal="0" districtId="1" GoBack="1" latitude="24.13466" longitude="120.65586" inDis="50" outDis="50" oid="AFFE0642B78B43A6992C7CAE901F88D6" /><Stop Id="0335" routeId="26" nameZh="下田心仔" seqNo="19" pgp="0" terminal="0" districtId="1" GoBack="1" latitude="24.1361" longitude="120.65166" inDis="50" outDis="50" oid="AD0024C9AD224E2791AD6E79DC67B315" /><Stop Id="0577" routeId="26" nameZh="田心仔" seqNo="20" pgp="0" terminal="0" districtId="1" GoBack="1" latitude="24.13699" longitude="120.64866" inDis="50" outDis="50" oid="D563E662E8104AF394BFE475B4791974" /><Stop Id="5134" routeId="26" nameZh="清真寺(南屯路)" seqNo="21" pgp="0" terminal="0" districtId="1" GoBack="1" latitude="24.13733" longitude="120.64701" inDis="50" outDis="50" oid="A24E637E31174BE9AF45CE01A359DF92" /><Stop Id="5507" routeId="26" nameZh="南屯向心路口" seqNo="22" pgp="0" terminal="0" districtId="1" GoBack="1" latitude="24.13815" longitude="120.64435" inDis="50" outDis="50" oid="315386763" /><Stop Id="4764" routeId="26" nameZh="第四分局" seqNo="23" pgp="0" terminal="0" districtId="1" GoBack="1" latitude="24.13478" longitude="120.64348" inDis="50" outDis="50" oid="307156377" /><Stop Id="0869" routeId="26" nameZh="萬和國中" seqNo="24" pgp="0" terminal="0" districtId="1" GoBack="1" latitude="24.13493" longitude="120.64079" inDis="50" outDis="50" oid="F82FC5BEA9284650A049C512E7440F49" /><Stop Id="4643" routeId="26" nameZh="黎明永春東路口" seqNo="25" pgp="0" terminal="0" districtId="1" GoBack="1" latitude="24.13534" longitude="120.63656" inDis="50" outDis="50" oid="BE2E740F9FD94ECCB34C7FE232E0419C" /><Stop Id="0478" routeId="26" nameZh="黎明文心南五路口" seqNo="26" pgp="0" terminal="0" districtId="1" GoBack="1" latitude="24.13289" longitude="120.63561" inDis="50" outDis="50" oid="04A992D3E4B444F88677FF9877B8D54A" /><Stop Id="0341" routeId="26" nameZh="下豐樂里" seqNo="27" pgp="0" terminal="0" districtId="1" GoBack="1" latitude="24.13062" longitude="120.63472" inDis="50" outDis="50" oid="26288FBC6533474D992810E415C09766" /><Stop Id="0953" routeId="26" nameZh="鎮平里" seqNo="28" pgp="0" terminal="0" districtId="1" GoBack="1" latitude="24.12862" longitude="120.63351" inDis="50" outDis="50" oid="DE2E8BE1D81D45D2A7209C71F9581B45" /><Stop Id="0955" routeId="26" nameZh="鎮平環中路口" seqNo="29" pgp="0" terminal="0" districtId="1" GoBack="1" latitude="24.12512" longitude="120.6314" inDis="50" outDis="50" oid="13045" /><Stop Id="0954" routeId="26" nameZh="鎮平國小" seqNo="30" pgp="0" terminal="0" districtId="1" GoBack="1" latitude="24.12115" longitude="120.62899" inDis="50" outDis="50" oid="E751418DBA294A7494B8390745E19BF5" /><Stop Id="0421" routeId="26" nameZh="中和" seqNo="31" pgp="0" terminal="0" districtId="1" GoBack="1" latitude="24.11837" longitude="120.62779" inDis="50" outDis="50" oid="549FB2AE735E409BBFCE2015C227404C" /><Stop Id="0645" routeId="26" nameZh="昌興新村" seqNo="32" pgp="0" terminal="0" districtId="1" GoBack="1" latitude="24.11592" longitude="120.62673" inDis="50" outDis="50" oid="7E91EA4B7BCB44F49D48440CA4436D7B" /><Stop Id="0422" routeId="26" nameZh="中和新村" seqNo="33" pgp="0" terminal="0" districtId="1" GoBack="1" latitude="24.11462" longitude="120.62629" inDis="50" outDis="50" oid="ED0AF9B723684B0E8A712979EC29885C" /><Stop Id="2819" routeId="26" nameZh="烏日啤酒廠" seqNo="34" pgp="0" terminal="0" districtId="1" GoBack="1" latitude="24.11198" longitude="120.62597" inDis="50" outDis="50" oid="5A980152EB744B6C95A36256FD0027C4" /><Stop Id="4915" routeId="26" nameZh="啤酒廠美食街" seqNo="35" pgp="0" terminal="0" districtId="1" GoBack="1" latitude="24.11046" longitude="120.62568" inDis="50" outDis="50" oid="307155817" /><Stop Id="2907" routeId="26" nameZh="高鐵台中站(15月台)" seqNo="38" pgp="0" terminal="0" districtId="1" GoBack="1" latitude="24.11117" longitude="120.61872" inDis="50" outDis="50" oid="310692254" /><Stop Id="4757" routeId="26" nameZh="幸記公司" seqNo="45" pgp="0" terminal="0" districtId="1" GoBack="1" latitude="24.11806" longitude="120.60802" inDis="50" outDis="50" oid="307153397" /><Stop Id="4758" routeId="26" nameZh="學田診所" seqNo="46" pgp="0" terminal="0" districtId="1" GoBack="1" latitude="24.12063" longitude="120.60777" inDis="50" outDis="50" oid="307153496" /><Stop Id="5472" routeId="26" nameZh="學田活動中心" seqNo="47" pgp="0" terminal="0" districtId="1" GoBack="1" latitude="24.12222" longitude="120.6073" inDis="50" outDis="50" oid="314251941" /><Stop Id="4759" routeId="26" nameZh="烏日學田里" seqNo="48" pgp="0" terminal="0" districtId="1" GoBack="1" latitude="24.12455" longitude="120.60689" inDis="50" outDis="50" oid="307153497" /><Stop Id="4760" routeId="26" nameZh="成功嶺3號門" seqNo="49" pgp="0" terminal="0" districtId="1" GoBack="1" latitude="24.12644" longitude="120.60748" inDis="50" outDis="50" oid="307153499" /><Stop Id="4964" routeId="26" nameZh="同安南北巷口" seqNo="50" pgp="0" terminal="0" districtId="1" GoBack="1" latitude="24.12914" longitude="120.60908" inDis="50" outDis="50" oid="308523039" /><Stop Id="4761" routeId="26" nameZh="南屯同安厝" seqNo="51" pgp="0" terminal="0" districtId="1" GoBack="1" latitude="24.13168" longitude="120.61049" inDis="50" outDis="50" oid="307153500" /><Stop Id="4762" routeId="26" nameZh="彩虹眷村" seqNo="52" pgp="0" terminal="0" districtId="1" GoBack="1" latitude="24.13403" longitude="120.61133" inDis="50" outDis="50" oid="307153501" /><Stop Id="4763" routeId="26" nameZh="春社派出所" seqNo="53" pgp="0" terminal="0" districtId="1" GoBack="1" latitude="24.13612" longitude="120.61191" inDis="50" outDis="50" oid="307153502" /><Stop Id="3874" routeId="26" nameZh="嶺東高中" seqNo="54" pgp="0" terminal="0" districtId="1" GoBack="1" latitude="24.13851" longitude="120.61141" inDis="50" outDis="50" oid="7C771850A3814FF691E283A433E21890" /><Stop Id="5162" routeId="26" nameZh="嶺東科技大學(永春南路)" seqNo="55" pgp="0" terminal="1" districtId="1" GoBack="1" latitude="24.13851" longitude="120.60906" inDis="50" outDis="50" oid="A5BA82E1E5D84D6996CBC2459367C9A8" /><Stop Id="5162" routeId="26" nameZh="嶺東科技大學(永春南路)" seqNo="1" pgp="0" terminal="0" districtId="1" GoBack="2" latitude="24.13851" longitude="120.60906" inDis="50" outDis="50" oid="A5BA82E1E5D84D6996CBC2459367C9A8" /><Stop Id="3874" routeId="26" nameZh="嶺東高中" seqNo="2" pgp="0" terminal="0" districtId="1" GoBack="2" latitude="24.13851" longitude="120.61141" inDis="50" outDis="50" oid="7C771850A3814FF691E283A433E21890" /><Stop Id="4763" routeId="26" nameZh="春社派出所" seqNo="3" pgp="0" terminal="0" districtId="1" GoBack="2" latitude="24.13612" longitude="120.61191" inDis="50" outDis="50" oid="307153502" /><Stop Id="4762" routeId="26" nameZh="彩虹眷村" seqNo="4" pgp="0" terminal="0" districtId="1" GoBack="2" latitude="24.13403" longitude="120.61133" inDis="50" outDis="50" oid="307153501" /><Stop Id="4761" routeId="26" nameZh="南屯同安厝" seqNo="5" pgp="0" terminal="0" districtId="1" GoBack="2" latitude="24.13168" longitude="120.61049" inDis="50" outDis="50" oid="307153500" /><Stop Id="4964" routeId="26" nameZh="同安南北巷口" seqNo="6" pgp="0" terminal="0" districtId="1" GoBack="2" latitude="24.12914" longitude="120.60908" inDis="50" outDis="50" oid="308523040" /><Stop Id="4760" routeId="26" nameZh="成功嶺3號門" seqNo="7" pgp="0" terminal="0" districtId="1" GoBack="2" latitude="24.12644" longitude="120.60748" inDis="50" outDis="50" oid="307153499" /><Stop Id="4759" routeId="26" nameZh="烏日學田里" seqNo="8" pgp="0" terminal="0" districtId="1" GoBack="2" latitude="24.12455" longitude="120.60689" inDis="50" outDis="50" oid="307153497" /><Stop Id="5472" routeId="26" nameZh="學田活動中心" seqNo="9" pgp="0" terminal="0" districtId="1" GoBack="2" latitude="24.12222" longitude="120.6073" inDis="50" outDis="50" oid="314251941" /><Stop Id="4758" routeId="26" nameZh="學田診所" seqNo="10" pgp="0" terminal="0" districtId="1" GoBack="2" latitude="24.12063" longitude="120.60777" inDis="50" outDis="50" oid="307153496" /><Stop Id="4757" routeId="26" nameZh="幸記公司" seqNo="11" pgp="0" terminal="0" districtId="1" GoBack="2" latitude="24.11806" longitude="120.60802" inDis="50" outDis="50" oid="307153397" /><Stop Id="2907" routeId="26" nameZh="高鐵台中站(15月台)" seqNo="18" pgp="0" terminal="0" districtId="1" GoBack="2" latitude="24.11117" longitude="120.61872" inDis="50" outDis="50" oid="310692254" /><Stop Id="4915" routeId="26" nameZh="啤酒廠美食街" seqNo="21" pgp="0" terminal="0" districtId="1" GoBack="2" latitude="24.11046" longitude="120.62568" inDis="50" outDis="50" oid="307155817" /><Stop Id="2819" routeId="26" nameZh="烏日啤酒廠" seqNo="22" pgp="0" terminal="0" districtId="1" GoBack="2" latitude="24.11211" longitude="120.62607" inDis="50" outDis="50" oid="5B98F1D18D4A4744BD6688A1A043C63B" /><Stop Id="0422" routeId="26" nameZh="中和新村" seqNo="23" pgp="0" terminal="0" districtId="1" GoBack="2" latitude="24.11376" longitude="120.62608" inDis="50" outDis="50" oid="A7A6355970C7452BB1CAE293B439074C" /><Stop Id="0645" routeId="26" nameZh="昌興新村" seqNo="24" pgp="0" terminal="0" districtId="1" GoBack="2" latitude="24.11655" longitude="120.62698" inDis="50" outDis="50" oid="C71D3EEFCDD54F77978400EDBD770476" /><Stop Id="0421" routeId="26" nameZh="中和" seqNo="25" pgp="0" terminal="0" districtId="1" GoBack="2" latitude="24.11826" longitude="120.62768" inDis="50" outDis="50" oid="72C18B971C844EF0B11E821595513140" /><Stop Id="0954" routeId="26" nameZh="鎮平國小" seqNo="26" pgp="0" terminal="0" districtId="1" GoBack="2" latitude="24.12111" longitude="120.6291" inDis="50" outDis="50" oid="C346F08338D846AC8331D97984AD49A8" /><Stop Id="0955" routeId="26" nameZh="鎮平環中路口" seqNo="27" pgp="0" terminal="0" districtId="1" GoBack="2" latitude="24.12512" longitude="120.6314" inDis="50" outDis="50" oid="13045" /><Stop Id="0953" routeId="26" nameZh="鎮平里" seqNo="28" pgp="0" terminal="0" districtId="1" GoBack="2" latitude="24.12868" longitude="120.63364" inDis="50" outDis="50" oid="76089C469CF044E783E2DAA74556ED16" /><Stop Id="0341" routeId="26" nameZh="下豐樂里" seqNo="29" pgp="0" terminal="0" districtId="1" GoBack="2" latitude="24.13075" longitude="120.63486" inDis="50" outDis="50" oid="34C39A690D5B41AE9CA5B774CB34FE65" /><Stop Id="0478" routeId="26" nameZh="黎明文心南五路口" seqNo="30" pgp="0" terminal="0" districtId="1" GoBack="2" latitude="24.13288" longitude="120.63572" inDis="50" outDis="50" oid="C35A3BC577CF491AA043CE8482C64D93" /><Stop Id="4643" routeId="26" nameZh="黎明永春東路口" seqNo="31" pgp="0" terminal="0" districtId="1" GoBack="2" latitude="24.13498" longitude="120.6365" inDis="50" outDis="50" oid="4B9BD0DF2F5B41A38F459C43AF4C9CF2" /><Stop Id="0869" routeId="26" nameZh="萬和國中" seqNo="32" pgp="0" terminal="0" districtId="1" GoBack="2" latitude="24.13481" longitude="120.6409" inDis="50" outDis="50" oid="9C6DBBB146F047AD812A9200C17EE86C" /><Stop Id="4764" routeId="26" nameZh="第四分局" seqNo="33" pgp="0" terminal="0" districtId="1" GoBack="2" latitude="24.13478" longitude="120.64348" inDis="50" outDis="50" oid="307156377" /><Stop Id="5507" routeId="26" nameZh="南屯向心路口" seqNo="34" pgp="0" terminal="0" districtId="1" GoBack="2" latitude="24.13815" longitude="120.64435" inDis="50" outDis="50" oid="315386763" /><Stop Id="5134" routeId="26" nameZh="清真寺(南屯路)" seqNo="35" pgp="0" terminal="0" districtId="1" GoBack="2" latitude="24.13733" longitude="120.64693" inDis="50" outDis="50" oid="F9541598379E475DA912B075896EBA4B" /><Stop Id="0577" routeId="26" nameZh="田心仔" seqNo="36" pgp="0" terminal="0" districtId="1" GoBack="2" latitude="24.13699" longitude="120.64866" inDis="50" outDis="50" oid="D563E662E8104AF394BFE475B4791974" /><Stop Id="0335" routeId="26" nameZh="下田心仔" seqNo="37" pgp="0" terminal="0" districtId="1" GoBack="2" latitude="24.13637" longitude="120.65083" inDis="50" outDis="50" oid="1FDBF1C2BDB042CCB7142A594A380D1C" /><Stop Id="0348" routeId="26" nameZh="土庫" seqNo="38" pgp="0" terminal="0" districtId="1" GoBack="2" latitude="24.13453" longitude="120.65606" inDis="50" outDis="50" oid="FC4BD498E0194390B02799C15E47EA41" /><Stop Id="0126" routeId="26" nameZh="崇倫國中(南屯路)" seqNo="39" pgp="0" terminal="0" districtId="1" GoBack="2" latitude="24.13369" longitude="120.65783" inDis="50" outDis="50" oid="1ED8251962CC4E25AEDC2913430D08C2" /><Stop Id="0935" routeId="26" nameZh="靜和醫院" seqNo="40" pgp="0" terminal="0" districtId="1" GoBack="2" latitude="24.13325" longitude="120.65965" inDis="50" outDis="50" oid="978A8A2CF0644DBD89F749EDE47B299D" /><Stop Id="4637" routeId="26" nameZh="南屯美村路口" seqNo="41" pgp="0" terminal="0" districtId="1" GoBack="2" latitude="24.13231" longitude="120.6613" inDis="50" outDis="50" oid="9F41736633F6400D98638B1E52E54A78" /><Stop Id="0562" routeId="26" nameZh="永安市場" seqNo="42" pgp="0" terminal="0" districtId="1" GoBack="2" latitude="24.13219" longitude="120.66483" inDis="50" outDis="50" oid="38564D15D23B4956A5AC3334A1B87476" /><Stop Id="5661" routeId="26" nameZh="公館(三民路)" seqNo="43" pgp="0" terminal="0" districtId="1" GoBack="2" latitude="24.13271" longitude="120.6696" inDis="50" outDis="50" oid="AB4F06E191E6479BB278EF729F5E33A8" /><Stop Id="0673" routeId="26" nameZh="三民林森路口" seqNo="44" pgp="0" terminal="0" districtId="1" GoBack="2" latitude="24.1355" longitude="120.67253" inDis="50" outDis="50" oid="923738B5CFC84EFA9C12730F5A1B4D25" /><Stop Id="0210" routeId="26" nameZh="忠孝國小" seqNo="45" pgp="0" terminal="0" districtId="1" GoBack="2" latitude="24.13709" longitude="120.67409" inDis="50" outDis="50" oid="01E74E872FA34A7AB6ABB29605545998" /><Stop Id="0209" routeId="26" nameZh="臺中科大民生校區" seqNo="46" pgp="0" terminal="0" districtId="1" GoBack="2" latitude="24.139" longitude="120.67604" inDis="50" outDis="50" oid="10382" /><Stop Id="5026" routeId="26" nameZh="美榮藥局" seqNo="47" pgp="0" terminal="0" districtId="1" GoBack="2" latitude="24.14131" longitude="120.67838" inDis="50" outDis="50" oid="309504377" /><Stop Id="5506" routeId="26" nameZh="光復國小(三民路)" seqNo="48" pgp="0" terminal="0" districtId="1" GoBack="2" latitude="24.14368" longitude="120.68091" inDis="50" outDis="50" oid="315386762" /><Stop Id="4543" routeId="26" nameZh="臺中公園(三民路)" seqNo="49" pgp="0" terminal="0" districtId="1" GoBack="2" latitude="24.14543" longitude="120.68225" inDis="50" outDis="50" oid="63EAF147E19E4EFBA4DFDEA508F322EB" /><Stop Id="0045" routeId="26" nameZh="國立臺中科技大學" seqNo="50" pgp="0" terminal="0" districtId="1" GoBack="2" latitude="24.14952" longitude="120.68399" inDis="50" outDis="50" oid="FE8EBA076843484F8F7A53322F1A4FE3" /><Stop Id="0046" routeId="26" nameZh="中友百貨" seqNo="51" pgp="0" terminal="0" districtId="1" GoBack="2" latitude="24.15243" longitude="120.68517" inDis="50" outDis="50" oid="4910685A86494A31A43EE7855C80C89A" /><Stop Id="0047" routeId="26" nameZh="一心市場" seqNo="52" pgp="0" terminal="0" districtId="1" GoBack="2" latitude="24.15378" longitude="120.68569" inDis="50" outDis="50" oid="C1E16C3844D5444CB7634C7CCC39A59B" /><Stop Id="0934" routeId="26" nameZh="三民錦中街口" seqNo="53" pgp="0" terminal="0" districtId="1" GoBack="2" latitude="24.15556" longitude="120.6871" inDis="50" outDis="50" oid="A369F80BD1F74F92A75B79E3B1367FC9" /><Stop Id="4399" routeId="26" nameZh="新民高中(三民路)" seqNo="54" pgp="0" terminal="0" districtId="1" GoBack="2" latitude="24.15679" longitude="120.68854" inDis="50" outDis="50" oid="5D8465AD704C4BCA9BE028E448E27AA9" /></BusInfo></BusDynInfo>